{"player":[{"id":"1","name":"Matthias Bachinger","fname":"Matthias","lname":"Bachinger","key":[{"data":"52:9:,,,,,:0%,0%,0%,0%,0%,0%:35%,:87%,:0,0,0,0,0,0"},{"data":"139:7:,,,,,:0%,0%,0%,0%,0%,0%:33%,:87%,:0,0,0,0,0,0"},{"data":"97:5:,,,,,:0%,0%,0%,0%,0%,0%:60%,:87%,:0,0,0,0,0,0"}]},{"id":"2","name":"Andrea Collarini","fname":"Andrea","lname":"Collarini","key":[{"data":"74:7:,,,,,:0%,0%,0%,0%,0%,0%:11%,:87%,:1,1,1,1,1,1"},{"data":"65:7:,,,,,:0%,0%,0%,0%,0%,0%:32%,:87%,:1,1,1,1,1,1"},{"data":"136:6:,,,,,:0%,0%,0%,0%,0%,0%:77%,:87%,:0,0,0,0,0,0"}]}]}