{"player":[{"id":"1","name":"Evgeniya Rodina","fname":"Evgeniya","lname":"Rodina","key":[{"data":"52:6:,,,,,:0%,0%,0%,0%,0%,0%:39%,:87%,:0,0,0,0,0,0"},{"data":"19:5:,,,,,:0%,0%,0%,0%,0%,0%:57%,:87%,:0,0,0,0,0,0"},{"data":"97:3:,,,,,:0%,0%,0%,0%,0%,0%:64%,:87%,:0,0,0,0,0,0"}]},{"id":"2","name":"Qiang Wang","fname":"Qiang","lname":"Wang","key":[{"data":"19:7:,,,,,:0%,0%,0%,0%,0%,0%:66%,:87%,:0,0,0,0,0,0"},{"data":"52:5:,,,,,:0%,0%,0%,0%,0%,0%:35%,:87%,:0,0,0,0,0,0"},{"data":"1:4:,,,,,:0%,0%,0%,0%,0%,0%:6%,:87%,:0,0,0,0,0,0"}]}]}