{"player":[{"id":"1","name":"Evgeny Donskoy","fname":"Evgeny","lname":"Donskoy","key":[{"data":"19:7:/=,/=,/=,/=,/=,/=:0%,0%,0%,0%,0%,0%:74%,:87%,:0,0,0,0,0,0"},{"data":"52:4:/=,/=,/=,/=,/=,/=:0%,0%,0%,0%,0%,0%:28%,:87%,:0,0,0,0,0,0"},{"data":"1:4:/=,/=,/=,/=,/=,/=:0%,0%,0%,0%,0%,0%:11%,:87%,:0,0,0,0,0,0"},{"data":"97:3:/=,/=,/=,/=,/=,/=:0%,0%,0%,0%,0%,0%:64%,:87%,:0,0,0,0,0,0"},{"data":"35:2:/=,/=,/=,/=,/=,/=:0%,0%,0%,0%,0%,0%:6.4,:87%,:1,1,1,1,1,1"}]},{"id":"2","name":"Illya Marchenko","fname":"Illya","lname":"Marchenko","key":[{"data":"19:6:/=,/=,/=,/=,/=,/=:0%,0%,0%,0%,0%,0%:76%,:87%,:0,0,0,0,0,0"},{"data":"52:6:/=,/=,/=,/=,/=,/=:0%,0%,0%,0%,0%,0%:32%,:87%,:0,0,0,0,0,0"},{"data":"97:1:/=,/=,/=,/=,/=,/=:0%,0%,0%,0%,0%,0%:38%,:87%,:0,0,0,0,0,0"},{"data":"16:1:/=,/=,/=,/=,/=,/=:0%,0%,0%,0%,0%,0%:63%,:87%,:0,0,0,0,0,0"},{"data":"31:1:/=,/=,/=,/=,/=,/=:0%,0%,0%,0%,0%,0%:5.2,:87%,:0,0,0,0,0,0"}]}]}