{"player":[{"id":"1","name":"Dustin Brown","fname":"Dustin","lname":"Brown","key":[{"data":"145:5:48%,38%,45%,67%,50%,0%:48%,38%,45%,67%,50%,0%:48%,:48%,:1,0,0,1,1,0"},{"data":"19:5:72%,68%,70%,79%,71%,0%:72%,68%,70%,79%,71%,0%:76%,:76%,:0,0,0,1,0,0"},{"data":"52:5:23%,6%,29%,33%,24%,0%:23%,6%,29%,33%,24%,0%:26%,:26%,:0,0,1,1,0,0"}]},{"id":"2","name":"Marcos Baghdatis","fname":"Marcos","lname":"Baghdatis","key":[{"data":"19:6:77%,94%,71%,67%,76%,0%:77%,94%,71%,67%,76%,0%:77%,:77%,:1,1,0,0,2,0"},{"data":"145:6:52%,62%,55%,33%,50%,0%:52%,62%,55%,33%,50%,0%:52%,:52%,:1,1,1,0,2,0"},{"data":"52:5:28%,32%,30%,21%,29%,0%:28%,32%,30%,21%,29%,0%:26%,:26%,:1,1,1,0,1,0"}]}]}