{"player":[{"id":"1","name":"Stan Wawrinka","fname":"Stan","lname":"Wawrinka","key":[{"data":"19:6:79%,81%,76%,69%,89%,0%:79%,81%,76%,69%,89%,0%:76%,:76%,:1,1,1,0,1,0"},{"data":"145:6:58%,53%,72%,55%,56%,0%:58%,53%,72%,55%,56%,0%:54%,:54%,:1,2,1,1,1,0"},{"data":"52:4:36%,42%,41%,25%,30%,0%:36%,42%,41%,25%,30%,0%:26%,:26%,:1,1,1,2,1,0"}]},{"id":"2","name":"Yen-Hsun Lu","fname":"Yen-Hsun","lname":"Lu","key":[{"data":"19:6:64%,58%,59%,75%,70%,0%:64%,58%,59%,75%,70%,0%:71%,:71%,:0,0,0,1,2,0"},{"data":"145:5:42%,47%,28%,45%,44%,0%:42%,47%,28%,45%,44%,0%:46%,:46%,:0,1,0,2,2,0"},{"data":"52:3:21%,19%,24%,31%,11%,0%:21%,19%,24%,31%,11%,0%:24%,:24%,:0,0,1,1,0,0"}]}]}