{"player":[{"id":"1","name":"Lucie Safarova","fname":"Lucie","lname":"Safarova","key":[{"data":"19:5:81%,82%,80%,0%,0%,0%:81%,82%,80%,0%,0%,0%:68%,:68%,:1,1,1,0,0,0"},{"data":"139:5:31%,29%,33%,0%,0%,0%:31%,29%,33%,0%,0%,0%:32%,:32%,:2,0,1,0,0,0"},{"data":"55:5:64%,53%,79%,0%,0%,0%:64%,53%,79%,0%,0%,0%:58%,:58%,:1,0,1,0,0,0"}]},{"id":"2","name":"Polona Hercog","fname":"Polona","lname":"Hercog","key":[{"data":"136:6:69%,71%,67%,0%,0%,0%:69%,71%,67%,0%,0%,0%:71%,:71%,:2,1,0,0,0,0"},{"data":"52:5:19%,18%,20%,0%,0%,0%:19%,18%,20%,0%,0%,0%:30%,:30%,:0,0,0,0,0,0"},{"data":"19:4:69%,70%,68%,0%,0%,0%:69%,70%,68%,0%,0%,0%:68%,:68%,:1,1,1,0,0,0"}]}]}