[{"ElapsedTime":"0:00:00","SetNo":"1","P1GamesWon":"0","P2GamesWon":"0","SetWinner":"0","GameNo":"1","GameWinner":"0","PointNumber":"0","PointWinner":"0","PointServer":"0","Speed_KMH":"0","P1Score":"0","P2Score":"0","P1PointsWon":"0","P2PointsWon":"0","Ace":"0","Winner":"0","DoubleFault":"0","UnforcedError":"0","NetPoint":"0","BreakPoint":"0","BreakPointWon":"0","History":"","Speed_MPH":"0","ServeIndicator":"0","ServeNumber":"0","WinnerType":"0","WinnerShotType":"0","Court":"","BreakPointOpportunity":"0","Stage":"inf"},{"ElapsedTime":"0:00:00","SetNo":"1","P1GamesWon":"0","P2GamesWon":"0","SetWinner":"0","GameNo":"1","GameWinner":"0","PointNumber":"1","PointWinner":"1","PointServer":"1","Speed_KMH":"0","P1Score":"15","P2Score":"0","P1PointsWon":"0","P2PointsWon":"0","Ace":"0","Winner":"0","DoubleFault":"0","UnforcedError":"0","NetPoint":"0","BreakPoint":"0","BreakPointWon":"0","History":"22030","Speed_MPH":"0","ServeIndicator":"1","ServeNumber":"1","WinnerType":"0","WinnerShotType":"0","Court":"D","BreakPointOpportunity":"0","Stage":"fer,pwm"},{"ElapsedTime":"0:00:13","SetNo":"1","P1GamesWon":"0","P2GamesWon":"0","SetWinner":"0","GameNo":"1","GameWinner":"0","PointNumber":"2","PointWinner":"2","PointServer":"1","Speed_KMH":"0","P1Score":"15","P2Score":"15","P1PointsWon":"0","P2PointsWon":"0","Ace":"0","Winner":"0","DoubleFault":"1","UnforcedError":"1","NetPoint":"0","BreakPoint":"0","BreakPointWon":"0","History":"15000","Speed_MPH":"0","ServeIndicator":"1","ServeNumber":"0","WinnerType":"0","WinnerShotType":"0","Court":"A","BreakPointOpportunity":"0","Stage":"dbf"},{"ElapsedTime":"0:00:54","SetNo":"1","P1GamesWon":"0","P2GamesWon":"0","SetWinner":"0","GameNo":"1","GameWinner":"0","PointNumber":"3","PointWinner":"2","PointServer":"1","Speed_KMH":"0","P1Score":"15","P2Score":"30","P1PointsWon":"0","P2PointsWon":"0","Ace":"0","Winner":"0","DoubleFault":"0","UnforcedError":"1","NetPoint":"0","BreakPoint":"0","BreakPointWon":"0","History":"11020","Speed_MPH":"0","ServeIndicator":"1","ServeNumber":"1","WinnerType":"0","WinnerShotType":"0","Court":"D","BreakPointOpportunity":"0","Stage":"uer,pwm"},{"ElapsedTime":"0:01:15","SetNo":"1","P1GamesWon":"0","P2GamesWon":"0","SetWinner":"0","GameNo":"1","GameWinner":"0","PointNumber":"4","PointWinner":"1","PointServer":"1","Speed_KMH":"0","P1Score":"30","P2Score":"30","P1PointsWon":"0","P2PointsWon":"0","Ace":"0","Winner":"0","DoubleFault":"0","UnforcedError":"2","NetPoint":"0","BreakPoint":"0","BreakPointWon":"0","History":"21020","Speed_MPH":"0","ServeIndicator":"1","ServeNumber":"2","WinnerType":"0","WinnerShotType":"0","Court":"A","BreakPointOpportunity":"0","Stage":"uer,pwm"},{"ElapsedTime":"0:02:01","SetNo":"1","P1GamesWon":"0","P2GamesWon":"0","SetWinner":"0","GameNo":"1","GameWinner":"0","PointNumber":"5","PointWinner":"2","PointServer":"1","Speed_KMH":"0","P1Score":"30","P2Score":"40","P1PointsWon":"0","P2PointsWon":"0","Ace":"0","Winner":"0","DoubleFault":"0","UnforcedError":"1","NetPoint":"0","BreakPoint":"0","BreakPointWon":"0","History":"11520","Speed_MPH":"0","ServeIndicator":"1","ServeNumber":"1","WinnerType":"0","WinnerShotType":"0","Court":"D","BreakPointOpportunity":"2","Stage":"uer,pwm"},{"ElapsedTime":"0:02:27","SetNo":"1","P1GamesWon":"0","P2GamesWon":"0","SetWinner":"0","GameNo":"1","GameWinner":"0","PointNumber":"6","PointWinner":"1","PointServer":"1","Speed_KMH":"0","P1Score":"40","P2Score":"40","P1PointsWon":"0","P2PointsWon":"0","Ace":"0","Winner":"0","DoubleFault":"0","UnforcedError":"0","NetPoint":"0","BreakPoint":"2","BreakPointWon":"0","History":"22030","Speed_MPH":"0","ServeIndicator":"1","ServeNumber":"1","WinnerType":"0","WinnerShotType":"0","Court":"A","BreakPointOpportunity":"0","Stage":"fer,pwm,bpw"},{"ElapsedTime":"0:02:50","SetNo":"1","P1GamesWon":"0","P2GamesWon":"0","SetWinner":"0","GameNo":"1","GameWinner":"0","PointNumber":"7","PointWinner":"2","PointServer":"1","Speed_KMH":"0","P1Score":"40","P2Score":"AD","P1PointsWon":"0","P2PointsWon":"0","Ace":"0","Winner":"0","DoubleFault":"0","UnforcedError":"0","NetPoint":"0","BreakPoint":"0","BreakPointWon":"0","History":"12030","Speed_MPH":"0","ServeIndicator":"1","ServeNumber":"2","WinnerType":"0","WinnerShotType":"0","Court":"D","BreakPointOpportunity":"2","Stage":"fer,pwm"},{"ElapsedTime":"0:03:21","SetNo":"1","P1GamesWon":"0","P2GamesWon":"1","SetWinner":"0","GameNo":"1","GameWinner":"2","PointNumber":"8","PointWinner":"2","PointServer":"1","Speed_KMH":"0","P1Score":"0","P2Score":"0","P1PointsWon":"0","P2PointsWon":"0","Ace":"0","Winner":"2","DoubleFault":"0","UnforcedError":"0","NetPoint":"0","BreakPoint":"2","BreakPointWon":"2","History":"21011","Speed_MPH":"0","ServeIndicator":"2","ServeNumber":"2","WinnerType":"0","WinnerShotType":"F","Court":"A","BreakPointOpportunity":"0","Stage":"fsp,fsw,ssw,rpw,bpo"},{"ElapsedTime":"0:04:33","SetNo":"1","P1GamesWon":"0","P2GamesWon":"1","SetWinner":"0","GameNo":"2","GameWinner":"0","PointNumber":"9","PointWinner":"2","PointServer":"2","Speed_KMH":"0","P1Score":"0","P2Score":"15","P1PointsWon":"0","P2PointsWon":"0","Ace":"2","Winner":"2","DoubleFault":"0","UnforcedError":"0","NetPoint":"0","BreakPoint":"0","BreakPointWon":"0","History":"23000","Speed_MPH":"0","ServeIndicator":"2","ServeNumber":"1","WinnerType":"0","WinnerShotType":"0","Court":"D","BreakPointOpportunity":"0","Stage":"ace"},{"ElapsedTime":"0:04:53","SetNo":"1","P1GamesWon":"0","P2GamesWon":"1","SetWinner":"0","GameNo":"2","GameWinner":"0","PointNumber":"10","PointWinner":"1","PointServer":"2","Speed_KMH":"0","P1Score":"15","P2Score":"15","P1PointsWon":"0","P2PointsWon":"0","Ace":"0","Winner":"0","DoubleFault":"0","UnforcedError":"0","NetPoint":"0","BreakPoint":"0","BreakPointWon":"0","History":"22030","Speed_MPH":"0","ServeIndicator":"2","ServeNumber":"1","WinnerType":"0","WinnerShotType":"0","Court":"A","BreakPointOpportunity":"0","Stage":"fer,pwm"},{"ElapsedTime":"0:05:11","SetNo":"1","P1GamesWon":"0","P2GamesWon":"1","SetWinner":"0","GameNo":"2","GameWinner":"0","PointNumber":"11","PointWinner":"2","PointServer":"2","Speed_KMH":"0","P1Score":"15","P2Score":"30","P1PointsWon":"0","P2PointsWon":"0","Ace":"0","Winner":"0","DoubleFault":"0","UnforcedError":"0","NetPoint":"0","BreakPoint":"0","BreakPointWon":"0","History":"12030","Speed_MPH":"0","ServeIndicator":"2","ServeNumber":"1","WinnerType":"0","WinnerShotType":"0","Court":"D","BreakPointOpportunity":"0","Stage":"fer,pwm"},{"ElapsedTime":"0:05:29","SetNo":"1","P1GamesWon":"0","P2GamesWon":"1","SetWinner":"0","GameNo":"2","GameWinner":"0","PointNumber":"12","PointWinner":"2","PointServer":"2","Speed_KMH":"0","P1Score":"15","P2Score":"40","P1PointsWon":"0","P2PointsWon":"0","Ace":"0","Winner":"0","DoubleFault":"0","UnforcedError":"0","NetPoint":"0","BreakPoint":"0","BreakPointWon":"0","History":"12030","Speed_MPH":"0","ServeIndicator":"2","ServeNumber":"1","WinnerType":"0","WinnerShotType":"0","Court":"A","BreakPointOpportunity":"0","Stage":"fer,pwm"},{"ElapsedTime":"0:05:49","SetNo":"1","P1GamesWon":"0","P2GamesWon":"1","SetWinner":"0","GameNo":"2","GameWinner":"0","PointNumber":"13","PointWinner":"1","PointServer":"2","Speed_KMH":"0","P1Score":"30","P2Score":"40","P1PointsWon":"0","P2PointsWon":"0","Ace":"0","Winner":"0","DoubleFault":"0","UnforcedError":"0","NetPoint":"0","BreakPoint":"0","BreakPointWon":"0","History":"22030","Speed_MPH":"0","ServeIndicator":"2","ServeNumber":"2","WinnerType":"0","WinnerShotType":"0","Court":"D","BreakPointOpportunity":"0","Stage":"fer,pwm"},{"ElapsedTime":"0:06:26","SetNo":"1","P1GamesWon":"0","P2GamesWon":"1","SetWinner":"0","GameNo":"2","GameWinner":"0","PointNumber":"14","PointWinner":"1","PointServer":"2","Speed_KMH":"0","P1Score":"40","P2Score":"40","P1PointsWon":"0","P2PointsWon":"0","Ace":"0","Winner":"1","DoubleFault":"0","UnforcedError":"0","NetPoint":"0","BreakPoint":"0","BreakPointWon":"0","History":"11510","Speed_MPH":"0","ServeIndicator":"2","ServeNumber":"2","WinnerType":"0","WinnerShotType":"F","Court":"A","BreakPointOpportunity":"0","Stage":"win,pwm"},{"ElapsedTime":"0:07:07","SetNo":"1","P1GamesWon":"0","P2GamesWon":"1","SetWinner":"0","GameNo":"2","GameWinner":"0","PointNumber":"15","PointWinner":"1","PointServer":"2","Speed_KMH":"0","P1Score":"AD","P2Score":"40","P1PointsWon":"0","P2PointsWon":"0","Ace":"0","Winner":"0","DoubleFault":"0","UnforcedError":"2","NetPoint":"0","BreakPoint":"0","BreakPointWon":"0","History":"22020","Speed_MPH":"0","ServeIndicator":"2","ServeNumber":"2","WinnerType":"0","WinnerShotType":"0","Court":"D","BreakPointOpportunity":"1","Stage":"uer,pwm"},{"ElapsedTime":"0:07:44","SetNo":"1","P1GamesWon":"0","P2GamesWon":"1","SetWinner":"0","GameNo":"2","GameWinner":"0","PointNumber":"16","PointWinner":"2","PointServer":"2","Speed_KMH":"0","P1Score":"40","P2Score":"40","P1PointsWon":"0","P2PointsWon":"0","Ace":"0","Winner":"0","DoubleFault":"0","UnforcedError":"0","NetPoint":"0","BreakPoint":"1","BreakPointWon":"0","History":"12030","Speed_MPH":"0","ServeIndicator":"2","ServeNumber":"2","WinnerType":"0","WinnerShotType":"0","Court":"A","BreakPointOpportunity":"0","Stage":"fer,pwm,bpw"},{"ElapsedTime":"0:08:30","SetNo":"1","P1GamesWon":"0","P2GamesWon":"1","SetWinner":"0","GameNo":"2","GameWinner":"0","PointNumber":"17","PointWinner":"2","PointServer":"2","Speed_KMH":"0","P1Score":"40","P2Score":"AD","P1PointsWon":"0","P2PointsWon":"0","Ace":"0","Winner":"0","DoubleFault":"0","UnforcedError":"0","NetPoint":"0","BreakPoint":"0","BreakPointWon":"0","History":"12030","Speed_MPH":"0","ServeIndicator":"2","ServeNumber":"1","WinnerType":"0","WinnerShotType":"0","Court":"D","BreakPointOpportunity":"0","Stage":"fer,pwm"},{"ElapsedTime":"0:08:46","SetNo":"1","P1GamesWon":"0","P2GamesWon":"1","SetWinner":"0","GameNo":"2","GameWinner":"0","PointNumber":"18","PointWinner":"1","PointServer":"2","Speed_KMH":"0","P1Score":"40","P2Score":"40","P1PointsWon":"0","P2PointsWon":"0","Ace":"0","Winner":"0","DoubleFault":"0","UnforcedError":"0","NetPoint":"0","BreakPoint":"0","BreakPointWon":"0","History":"22030","Speed_MPH":"0","ServeIndicator":"2","ServeNumber":"2","WinnerType":"0","WinnerShotType":"0","Court":"A","BreakPointOpportunity":"0","Stage":"fer,pwm"},{"ElapsedTime":"0:09:24","SetNo":"1","P1GamesWon":"0","P2GamesWon":"1","SetWinner":"0","GameNo":"2","GameWinner":"0","PointNumber":"19","PointWinner":"2","PointServer":"2","Speed_KMH":"0","P1Score":"40","P2Score":"AD","P1PointsWon":"0","P2PointsWon":"0","Ace":"0","Winner":"0","DoubleFault":"0","UnforcedError":"1","NetPoint":"0","BreakPoint":"0","BreakPointWon":"0","History":"12020","Speed_MPH":"0","ServeIndicator":"2","ServeNumber":"1","WinnerType":"0","WinnerShotType":"0","Court":"D","BreakPointOpportunity":"0","Stage":"uer,pwm"},{"ElapsedTime":"0:09:47","SetNo":"1","P1GamesWon":"0","P2GamesWon":"2","SetWinner":"0","GameNo":"2","GameWinner":"2","PointNumber":"20","PointWinner":"2","PointServer":"2","Speed_KMH":"0","P1Score":"0","P2Score":"0","P1PointsWon":"0","P2PointsWon":"0","Ace":"2","Winner":"2","DoubleFault":"0","UnforcedError":"0","NetPoint":"0","BreakPoint":"0","BreakPointWon":"0","History":"23002","Speed_MPH":"0","ServeIndicator":"1","ServeNumber":"1","WinnerType":"0","WinnerShotType":"0","Court":"A","BreakPointOpportunity":"0","Stage":"fsp,fsw,ssw,rpw,bpo"},{"ElapsedTime":"0:10:15","SetNo":"1","P1GamesWon":"0","P2GamesWon":"2","SetWinner":"0","GameNo":"3","GameWinner":"0","PointNumber":"21","PointWinner":"2","PointServer":"1","Speed_KMH":"0","P1Score":"0","P2Score":"15","P1PointsWon":"0","P2PointsWon":"0","Ace":"0","Winner":"0","DoubleFault":"0","UnforcedError":"1","NetPoint":"0","BreakPoint":"0","BreakPointWon":"0","History":"12020","Speed_MPH":"0","ServeIndicator":"1","ServeNumber":"2","WinnerType":"0","WinnerShotType":"0","Court":"D","BreakPointOpportunity":"0","Stage":"uer,pwm"},{"ElapsedTime":"0:11:00","SetNo":"1","P1GamesWon":"0","P2GamesWon":"2","SetWinner":"0","GameNo":"3","GameWinner":"0","PointNumber":"22","PointWinner":"2","PointServer":"1","Speed_KMH":"0","P1Score":"0","P2Score":"30","P1PointsWon":"0","P2PointsWon":"0","Ace":"0","Winner":"2","DoubleFault":"0","UnforcedError":"0","NetPoint":"0","BreakPoint":"0","BreakPointWon":"0","History":"21010","Speed_MPH":"0","ServeIndicator":"1","ServeNumber":"1","WinnerType":"0","WinnerShotType":"F","Court":"A","BreakPointOpportunity":"0","Stage":"fhw,win,pwm"},{"ElapsedTime":"0:11:25","SetNo":"1","P1GamesWon":"0","P2GamesWon":"2","SetWinner":"0","GameNo":"3","GameWinner":"0","PointNumber":"23","PointWinner":"1","PointServer":"1","Speed_KMH":"0","P1Score":"15","P2Score":"30","P1PointsWon":"0","P2PointsWon":"0","Ace":"0","Winner":"0","DoubleFault":"0","UnforcedError":"0","NetPoint":"0","BreakPoint":"0","BreakPointWon":"0","History":"21030","Speed_MPH":"0","ServeIndicator":"1","ServeNumber":"2","WinnerType":"0","WinnerShotType":"0","Court":"D","BreakPointOpportunity":"0","Stage":"fer,pwm"},{"ElapsedTime":"0:12:17","SetNo":"1","P1GamesWon":"0","P2GamesWon":"2","SetWinner":"0","GameNo":"3","GameWinner":"0","PointNumber":"24","PointWinner":"1","PointServer":"1","Speed_KMH":"0","P1Score":"30","P2Score":"30","P1PointsWon":"0","P2PointsWon":"0","Ace":"0","Winner":"0","DoubleFault":"0","UnforcedError":"2","NetPoint":"0","BreakPoint":"0","BreakPointWon":"0","History":"21020","Speed_MPH":"0","ServeIndicator":"1","ServeNumber":"1","WinnerType":"0","WinnerShotType":"0","Court":"A","BreakPointOpportunity":"0","Stage":"uer,pwm"},{"ElapsedTime":"0:12:39","SetNo":"1","P1GamesWon":"0","P2GamesWon":"2","SetWinner":"0","GameNo":"3","GameWinner":"0","PointNumber":"25","PointWinner":"1","PointServer":"1","Speed_KMH":"0","P1Score":"40","P2Score":"30","P1PointsWon":"0","P2PointsWon":"0","Ace":"0","Winner":"0","DoubleFault":"0","UnforcedError":"0","NetPoint":"0","BreakPoint":"0","BreakPointWon":"0","History":"21030","Speed_MPH":"0","ServeIndicator":"1","ServeNumber":"1","WinnerType":"0","WinnerShotType":"0","Court":"D","BreakPointOpportunity":"0","Stage":"fer,pwm"},{"ElapsedTime":"0:12:55","SetNo":"1","P1GamesWon":"0","P2GamesWon":"2","SetWinner":"0","GameNo":"3","GameWinner":"0","PointNumber":"26","PointWinner":"2","PointServer":"1","Speed_KMH":"0","P1Score":"40","P2Score":"40","P1PointsWon":"0","P2PointsWon":"0","Ace":"0","Winner":"2","DoubleFault":"0","UnforcedError":"0","NetPoint":"0","BreakPoint":"0","BreakPointWon":"0","History":"21010","Speed_MPH":"0","ServeIndicator":"1","ServeNumber":"2","WinnerType":"0","WinnerShotType":"F","Court":"A","BreakPointOpportunity":"0","Stage":"fhw,win,pwm"},{"ElapsedTime":"0:13:39","SetNo":"1","P1GamesWon":"0","P2GamesWon":"2","SetWinner":"0","GameNo":"3","GameWinner":"0","PointNumber":"27","PointWinner":"1","PointServer":"1","Speed_KMH":"0","P1Score":"AD","P2Score":"40","P1PointsWon":"0","P2PointsWon":"0","Ace":"0","Winner":"1","DoubleFault":"0","UnforcedError":"0","NetPoint":"0","BreakPoint":"0","BreakPointWon":"0","History":"11010","Speed_MPH":"0","ServeIndicator":"1","ServeNumber":"1","WinnerType":"0","WinnerShotType":"F","Court":"D","BreakPointOpportunity":"0","Stage":"fhw,win,pwm"},{"ElapsedTime":"0:14:04","SetNo":"1","P1GamesWon":"0","P2GamesWon":"2","SetWinner":"0","GameNo":"3","GameWinner":"0","PointNumber":"28","PointWinner":"2","PointServer":"1","Speed_KMH":"0","P1Score":"40","P2Score":"40","P1PointsWon":"0","P2PointsWon":"0","Ace":"0","Winner":"0","DoubleFault":"0","UnforcedError":"1","NetPoint":"0","BreakPoint":"0","BreakPointWon":"0","History":"12020","Speed_MPH":"0","ServeIndicator":"1","ServeNumber":"1","WinnerType":"0","WinnerShotType":"0","Court":"A","BreakPointOpportunity":"0","Stage":"uer,pwm"},{"ElapsedTime":"0:14:30","SetNo":"1","P1GamesWon":"0","P2GamesWon":"2","SetWinner":"0","GameNo":"3","GameWinner":"0","PointNumber":"29","PointWinner":"2","PointServer":"1","Speed_KMH":"0","P1Score":"40","P2Score":"AD","P1PointsWon":"0","P2PointsWon":"0","Ace":"0","Winner":"0","DoubleFault":"0","UnforcedError":"0","NetPoint":"0","BreakPoint":"0","BreakPointWon":"0","History":"12030","Speed_MPH":"0","ServeIndicator":"1","ServeNumber":"2","WinnerType":"0","WinnerShotType":"0","Court":"D","BreakPointOpportunity":"2","Stage":"fer,pwm"},{"ElapsedTime":"0:15:46","SetNo":"1","P1GamesWon":"0","P2GamesWon":"2","SetWinner":"0","GameNo":"3","GameWinner":"0","PointNumber":"30","PointWinner":"1","PointServer":"1","Speed_KMH":"0","P1Score":"40","P2Score":"40","P1PointsWon":"0","P2PointsWon":"0","Ace":"0","Winner":"0","DoubleFault":"0","UnforcedError":"0","NetPoint":"0","BreakPoint":"2","BreakPointWon":"0","History":"22030","Speed_MPH":"0","ServeIndicator":"1","ServeNumber":"1","WinnerType":"0","WinnerShotType":"0","Court":"A","BreakPointOpportunity":"0","Stage":"fer,pwm,bpw"},{"ElapsedTime":"0:16:11","SetNo":"1","P1GamesWon":"0","P2GamesWon":"2","SetWinner":"0","GameNo":"3","GameWinner":"0","PointNumber":"31","PointWinner":"1","PointServer":"1","Speed_KMH":"0","P1Score":"AD","P2Score":"40","P1PointsWon":"0","P2PointsWon":"0","Ace":"0","Winner":"1","DoubleFault":"0","UnforcedError":"0","NetPoint":"0","BreakPoint":"0","BreakPointWon":"0","History":"11010","Speed_MPH":"0","ServeIndicator":"1","ServeNumber":"1","WinnerType":"0","WinnerShotType":"F","Court":"D","BreakPointOpportunity":"0","Stage":"fhw,win,pwm"},{"ElapsedTime":"0:16:33","SetNo":"1","P1GamesWon":"0","P2GamesWon":"2","SetWinner":"0","GameNo":"3","GameWinner":"0","PointNumber":"32","PointWinner":"2","PointServer":"1","Speed_KMH":"0","P1Score":"40","P2Score":"40","P1PointsWon":"0","P2PointsWon":"0","Ace":"0","Winner":"0","DoubleFault":"1","UnforcedError":"1","NetPoint":"0","BreakPoint":"0","BreakPointWon":"0","History":"15000","Speed_MPH":"0","ServeIndicator":"1","ServeNumber":"0","WinnerType":"0","WinnerShotType":"0","Court":"A","BreakPointOpportunity":"0","Stage":"dbf"},{"ElapsedTime":"0:17:03","SetNo":"1","P1GamesWon":"0","P2GamesWon":"2","SetWinner":"0","GameNo":"3","GameWinner":"0","PointNumber":"33","PointWinner":"2","PointServer":"1","Speed_KMH":"0","P1Score":"40","P2Score":"AD","P1PointsWon":"0","P2PointsWon":"0","Ace":"0","Winner":"0","DoubleFault":"0","UnforcedError":"0","NetPoint":"0","BreakPoint":"0","BreakPointWon":"0","History":"12030","Speed_MPH":"0","ServeIndicator":"1","ServeNumber":"2","WinnerType":"0","WinnerShotType":"0","Court":"D","BreakPointOpportunity":"2","Stage":"fer,pwm"},{"ElapsedTime":"0:17:31","SetNo":"1","P1GamesWon":"0","P2GamesWon":"3","SetWinner":"0","GameNo":"3","GameWinner":"2","PointNumber":"34","PointWinner":"2","PointServer":"1","Speed_KMH":"0","P1Score":"0","P2Score":"0","P1PointsWon":"0","P2PointsWon":"0","Ace":"0","Winner":"0","DoubleFault":"0","UnforcedError":"1","NetPoint":"0","BreakPoint":"2","BreakPointWon":"2","History":"12021","Speed_MPH":"0","ServeIndicator":"2","ServeNumber":"2","WinnerType":"0","WinnerShotType":"0","Court":"A","BreakPointOpportunity":"0","Stage":"fsp,fsw,ssw,rpw,bpo"},{"ElapsedTime":"0:19:19","SetNo":"1","P1GamesWon":"0","P2GamesWon":"3","SetWinner":"0","GameNo":"4","GameWinner":"0","PointNumber":"35","PointWinner":"2","PointServer":"2","Speed_KMH":"0","P1Score":"0","P2Score":"15","P1PointsWon":"0","P2PointsWon":"0","Ace":"0","Winner":"0","DoubleFault":"0","UnforcedError":"0","NetPoint":"0","BreakPoint":"0","BreakPointWon":"0","History":"12030","Speed_MPH":"0","ServeIndicator":"2","ServeNumber":"1","WinnerType":"0","WinnerShotType":"0","Court":"D","BreakPointOpportunity":"0","Stage":"fer,pwm"},{"ElapsedTime":"0:19:37","SetNo":"1","P1GamesWon":"0","P2GamesWon":"3","SetWinner":"0","GameNo":"4","GameWinner":"0","PointNumber":"36","PointWinner":"1","PointServer":"2","Speed_KMH":"0","P1Score":"15","P2Score":"15","P1PointsWon":"0","P2PointsWon":"0","Ace":"0","Winner":"1","DoubleFault":"0","UnforcedError":"0","NetPoint":"0","BreakPoint":"0","BreakPointWon":"0","History":"11010","Speed_MPH":"0","ServeIndicator":"2","ServeNumber":"2","WinnerType":"0","WinnerShotType":"F","Court":"A","BreakPointOpportunity":"0","Stage":"fhw,win,pwm"},{"ElapsedTime":"0:20:22","SetNo":"1","P1GamesWon":"0","P2GamesWon":"3","SetWinner":"0","GameNo":"4","GameWinner":"0","PointNumber":"37","PointWinner":"2","PointServer":"2","Speed_KMH":"0","P1Score":"15","P2Score":"30","P1PointsWon":"0","P2PointsWon":"0","Ace":"0","Winner":"0","DoubleFault":"0","UnforcedError":"0","NetPoint":"0","BreakPoint":"0","BreakPointWon":"0","History":"11030","Speed_MPH":"0","ServeIndicator":"2","ServeNumber":"1","WinnerType":"0","WinnerShotType":"0","Court":"D","BreakPointOpportunity":"0","Stage":"fer,pwm"},{"ElapsedTime":"0:20:37","SetNo":"1","P1GamesWon":"0","P2GamesWon":"3","SetWinner":"0","GameNo":"4","GameWinner":"0","PointNumber":"38","PointWinner":"2","PointServer":"2","Speed_KMH":"0","P1Score":"15","P2Score":"40","P1PointsWon":"0","P2PointsWon":"0","Ace":"0","Winner":"0","DoubleFault":"0","UnforcedError":"1","NetPoint":"0","BreakPoint":"0","BreakPointWon":"0","History":"12020","Speed_MPH":"0","ServeIndicator":"2","ServeNumber":"2","WinnerType":"0","WinnerShotType":"0","Court":"A","BreakPointOpportunity":"0","Stage":"uer,pwm"},{"ElapsedTime":"0:21:10","SetNo":"1","P1GamesWon":"0","P2GamesWon":"4","SetWinner":"0","GameNo":"4","GameWinner":"2","PointNumber":"39","PointWinner":"2","PointServer":"2","Speed_KMH":"0","P1Score":"0","P2Score":"0","P1PointsWon":"0","P2PointsWon":"0","Ace":"0","Winner":"0","DoubleFault":"0","UnforcedError":"1","NetPoint":"0","BreakPoint":"0","BreakPointWon":"0","History":"12022","Speed_MPH":"0","ServeIndicator":"1","ServeNumber":"2","WinnerType":"0","WinnerShotType":"0","Court":"D","BreakPointOpportunity":"0","Stage":"fsp,fsw,ssw,rpw,bpo"},{"ElapsedTime":"0:21:51","SetNo":"1","P1GamesWon":"0","P2GamesWon":"4","SetWinner":"0","GameNo":"5","GameWinner":"0","PointNumber":"40","PointWinner":"2","PointServer":"1","Speed_KMH":"0","P1Score":"0","P2Score":"15","P1PointsWon":"0","P2PointsWon":"0","Ace":"0","Winner":"0","DoubleFault":"0","UnforcedError":"0","NetPoint":"0","BreakPoint":"0","BreakPointWon":"0","History":"11030","Speed_MPH":"0","ServeIndicator":"1","ServeNumber":"2","WinnerType":"0","WinnerShotType":"0","Court":"D","BreakPointOpportunity":"0","Stage":"fer,pwm"},{"ElapsedTime":"0:22:25","SetNo":"1","P1GamesWon":"0","P2GamesWon":"4","SetWinner":"0","GameNo":"5","GameWinner":"0","PointNumber":"41","PointWinner":"2","PointServer":"1","Speed_KMH":"0","P1Score":"0","P2Score":"30","P1PointsWon":"0","P2PointsWon":"0","Ace":"0","Winner":"2","DoubleFault":"0","UnforcedError":"0","NetPoint":"0","BreakPoint":"0","BreakPointWon":"0","History":"22010","Speed_MPH":"0","ServeIndicator":"1","ServeNumber":"2","WinnerType":"0","WinnerShotType":"B","Court":"A","BreakPointOpportunity":"0","Stage":"bhw,win,pwm"},{"ElapsedTime":"0:22:55","SetNo":"1","P1GamesWon":"0","P2GamesWon":"4","SetWinner":"0","GameNo":"5","GameWinner":"0","PointNumber":"42","PointWinner":"1","PointServer":"1","Speed_KMH":"0","P1Score":"15","P2Score":"30","P1PointsWon":"0","P2PointsWon":"0","Ace":"0","Winner":"0","DoubleFault":"0","UnforcedError":"0","NetPoint":"0","BreakPoint":"0","BreakPointWon":"0","History":"22030","Speed_MPH":"0","ServeIndicator":"1","ServeNumber":"2","WinnerType":"0","WinnerShotType":"0","Court":"D","BreakPointOpportunity":"0","Stage":"fer,pwm"},{"ElapsedTime":"0:23:30","SetNo":"1","P1GamesWon":"0","P2GamesWon":"4","SetWinner":"0","GameNo":"5","GameWinner":"0","PointNumber":"43","PointWinner":"2","PointServer":"1","Speed_KMH":"0","P1Score":"15","P2Score":"40","P1PointsWon":"0","P2PointsWon":"0","Ace":"0","Winner":"0","DoubleFault":"0","UnforcedError":"0","NetPoint":"0","BreakPoint":"0","BreakPointWon":"0","History":"12030","Speed_MPH":"0","ServeIndicator":"1","ServeNumber":"2","WinnerType":"0","WinnerShotType":"0","Court":"A","BreakPointOpportunity":"2","Stage":"fer,pwm"},{"ElapsedTime":"0:24:20","SetNo":"1","P1GamesWon":"0","P2GamesWon":"4","SetWinner":"0","GameNo":"5","GameWinner":"0","PointNumber":"44","PointWinner":"1","PointServer":"1","Speed_KMH":"0","P1Score":"30","P2Score":"40","P1PointsWon":"0","P2PointsWon":"0","Ace":"1","Winner":"1","DoubleFault":"0","UnforcedError":"0","NetPoint":"0","BreakPoint":"2","BreakPointWon":"0","History":"13000","Speed_MPH":"0","ServeIndicator":"1","ServeNumber":"1","WinnerType":"0","WinnerShotType":"0","Court":"D","BreakPointOpportunity":"2","Stage":"ace,bpw"},{"ElapsedTime":"0:24:44","SetNo":"1","P1GamesWon":"0","P2GamesWon":"5","SetWinner":"0","GameNo":"5","GameWinner":"2","PointNumber":"45","PointWinner":"2","PointServer":"1","Speed_KMH":"0","P1Score":"0","P2Score":"0","P1PointsWon":"0","P2PointsWon":"0","Ace":"0","Winner":"0","DoubleFault":"0","UnforcedError":"1","NetPoint":"0","BreakPoint":"2","BreakPointWon":"2","History":"11021","Speed_MPH":"0","ServeIndicator":"2","ServeNumber":"1","WinnerType":"0","WinnerShotType":"0","Court":"A","BreakPointOpportunity":"0","Stage":"fsp,fsw,ssw,rpw,bpo"}]