{"player":[{"id":"1","name":"Eugenie Bouchard","fname":"Eugenie","lname":"Bouchard","key":[{"data":"145:6:54%,68%,40%,0%,0%,0%:54%,68%,40%,0%,0%,0%:46%,:46%,:1,1,0,0,0,0"},{"data":"19:5:81%,76%,88%,0%,0%,0%:81%,76%,88%,0%,0%,0%:71%,:71%,:1,1,1,0,0,0"},{"data":"61:4:40%,52%,26%,0%,0%,0%:40%,52%,26%,0%,0%,0%:42%,:42%,:2,1,0,0,0,0"}]},{"id":"2","name":"Angelique Kerber","fname":"Angelique","lname":"Kerber","key":[{"data":"145:7:46%,32%,60%,0%,0%,0%:46%,32%,60%,0%,0%,0%:53%,:53%,:0,0,1,0,0,0"},{"data":"52:3:19%,24%,12%,0%,0%,0%:19%,24%,12%,0%,0%,0%:26%,:26%,:0,0,0,0,0,0"},{"data":"19:2:69%,80%,62%,0%,0%,0%:69%,80%,62%,0%,0%,0%:56%,:56%,:1,1,1,0,0,0"}]}]}