{"player":[{"id":"1","name":"Lourdes Dominguez Lino","fname":"Lourdes","lname":"Dominguez Lino","key":[{"data":"52:8:/=,/=,/=,/=,/=,/=:0%,0%,0%,0%,0%,0%:46%,:87%,:0,0,0,0,0,0"},{"data":"34:6:/=,/=,/=,/=,/=,/=:0%,0%,0%,0%,0%,0%:7.7,:87%,:0,0,0,0,0,0"},{"data":"19:5:/=,/=,/=,/=,/=,/=:0%,0%,0%,0%,0%,0%:57%,:87%,:0,0,0,0,0,0"},{"data":"16:4:/=,/=,/=,/=,/=,/=:0%,0%,0%,0%,0%,0%:68%,:87%,:0,0,0,0,0,0"},{"data":"97:2:/=,/=,/=,/=,/=,/=:0%,0%,0%,0%,0%,0%:43%,:87%,:0,0,0,0,0,0"}]},{"id":"2","name":"Shahar Peer","fname":"Shahar","lname":"Peer","key":[{"data":"66:6:/=,/=,/=,/=,/=,/=:0%,0%,0%,0%,0%,0%:9%,28%:28%,87%:0,0,0,0,0,0"},{"data":"52:6:/=,/=,/=,/=,/=,/=:0%,0%,0%,0%,0%,0%:46%,:87%,:0,0,0,0,0,0"},{"data":"19:5:/=,/=,/=,/=,/=,/=:0%,0%,0%,0%,0%,0%:58%,:87%,:0,0,0,0,0,0"},{"data":"16:3:/=,/=,/=,/=,/=,/=:0%,0%,0%,0%,0%,0%:70%,:87%,:0,0,0,0,0,0"},{"data":"32:1:/=,/=,/=,/=,/=,/=:0%,0%,0%,0%,0%,0%:6.7,:87%,:1,1,1,1,1,1"}]}]}