{"player":[{"id":"1","name":"Evgeny Donskoy","fname":"Evgeny","lname":"Donskoy","key":[{"data":"52:5:,,,,,:0%,0%,0%,0%,0%,0%:28%,:87%,:0,0,0,0,0,0"},{"data":"19:4:,,,,,:0%,0%,0%,0%,0%,0%:70%,:87%,:0,0,0,0,0,0"},{"data":"1:3:,,,,,:0%,0%,0%,0%,0%,0%:8%,:87%,:0,0,0,0,0,0"}]},{"id":"2","name":"Matt Reid","fname":"Matt","lname":"Reid","key":[{"data":"52:7:,,,,,:0%,0%,0%,0%,0%,0%:35%,:87%,:0,0,0,0,0,0"},{"data":"19:5:,,,,,:0%,0%,0%,0%,0%,0%:72%,:87%,:0,0,0,0,0,0"},{"data":"97:4:,,,,,:0%,0%,0%,0%,0%,0%:70%,:87%,:0,0,0,0,0,0"}]}]}