{"player":[{"id":"1","name":"Marc Gicquel","fname":"Marc","lname":"Gicquel","key":[{"data":"19:6:0%,0%,0%,0%,0%,0%:0%,0%,0%,0%,0%,0%:70%,:70%,:0,0,0,0,0,0"},{"data":"52:5:0%,0%,0%,0%,0%,0%:0%,0%,0%,0%,0%,0%:28%,:28%,:0,0,0,0,0,0"},{"data":"74:5:0%,0%,0%,0%,0%,0%:0%,0%,0%,0%,0%,0%:16%,:16%,:1,1,1,1,1,1"}]},{"id":"2","name":"Andreas Beck","fname":"Andreas","lname":"Beck","key":[{"data":"19:8:0%,0%,0%,0%,0%,0%:0%,0%,0%,0%,0%,0%:72%,:72%,:0,0,0,0,0,0"},{"data":"52:7:0%,0%,0%,0%,0%,0%:0%,0%,0%,0%,0%,0%:30%,:30%,:0,0,0,0,0,0"},{"data":"97:4:0%,0%,0%,0%,0%,0%:0%,0%,0%,0%,0%,0%:71%,:71%,:0,0,0,0,0,0"}]}]}