{"player":[{"id":"1","name":"Albert Ramos","fname":"Albert","lname":"Ramos","key":[{"data":"55:6:,,,,,:0%,0%,0%,0%,0%,0%:50%,:87%,:0,0,0,0,0,0"},{"data":"19:5:,,,,,:0%,0%,0%,0%,0%,0%:67%,:87%,:0,0,0,0,0,0"},{"data":"1:4:,,,,,:0%,0%,0%,0%,0%,0%:16%,:87%,:0,0,0,0,0,0"}]},{"id":"2","name":"Pablo Andujar","fname":"Pablo","lname":"Andujar","key":[{"data":"19:9:,,,,,:0%,0%,0%,0%,0%,0%:78%,:87%,:0,0,0,0,0,0"},{"data":"52:7:,,,,,:0%,0%,0%,0%,0%,0%:32%,:87%,:0,0,0,0,0,0"},{"data":"55:5:,,,,,:0%,0%,0%,0%,0%,0%:53%,:87%,:0,0,0,0,0,0"}]}]}