{"player":[{"id":"1","name":"Ekaterina Makarova","fname":"Ekaterina","lname":"Makarova","key":[{"data":"139:7:16%,0%,25%,17%,0%,0%:16%,0%,25%,17%,0%,0%:35%,:35%,:0,0,0,0,0,0"},{"data":"52:5:28%,18%,23%,35%,0%,0%:28%,18%,23%,35%,0%,0%:35%,:35%,:0,0,0,1,0,0"},{"data":"19:4:62%,42%,61%,84%,0%,0%:62%,42%,61%,84%,0%,0%:56%,:56%,:1,0,1,1,0,0"}]},{"id":"2","name":"Venus Williams","fname":"Venus","lname":"Williams","key":[{"data":"52:5:38%,58%,39%,16%,0%,0%:38%,58%,39%,16%,0%,0%:40%,:40%,:2,1,2,0,0,0"},{"data":"19:5:72%,82%,77%,65%,0%,0%:72%,82%,77%,65%,0%,0%:64%,:64%,:1,1,1,1,0,0"},{"data":"97:4:43%,50%,75%,25%,0%,0%:43%,50%,75%,25%,0%,0%:71%,:71%,:0,0,1,0,0,0"}]}]}