{"player":[{"id":"1","name":"Monica Niculescu","fname":"Monica","lname":"Niculescu","key":[{"data":"139:7:31%,42%,20%,33%,0%,0%:31%,42%,20%,33%,0%,0%:34%,:34%,:0,1,0,2,0,0"},{"data":"19:5:64%,38%,67%,76%,0%,0%:64%,38%,67%,76%,0%,0%:61%,:61%,:1,0,1,1,0,0"},{"data":"52:5:45%,47%,47%,38%,0%,0%:45%,47%,47%,38%,0%,0%:35%,:35%,:1,1,1,1,0,0"}]},{"id":"2","name":"Sabine Lisicki","fname":"Sabine","lname":"Lisicki","key":[{"data":"19:6:55%,53%,53%,63%,0%,0%:55%,53%,53%,63%,0%,0%:68%,:68%,:0,0,0,0,0,0"},{"data":"52:5:36%,62%,33%,24%,0%,0%:36%,62%,33%,24%,0%,0%:38%,:38%,:0,1,0,0,0,0"},{"data":"97:4:60%,100%,33%,0%,0%,0%:60%,100%,33%,0%,0%,0%:70%,:70%,:0,1,0,0,0,0"}]}]}