{"player":[{"id":"1","name":"Eugenie Bouchard","fname":"Eugenie","lname":"Bouchard","key":[{"data":"52:6:36%,23%,41%,0%,0%,0%:36%,23%,41%,0%,0%,0%:37%,:37%,:2,0,1,0,0,0"},{"data":"19:4:57%,38%,67%,0%,0%,0%:57%,38%,67%,0%,0%,0%:64%,:64%,:0,0,1,0,0,0"},{"data":"145:4:40%,25%,47%,0%,0%,0%:40%,25%,47%,0%,0%,0%:42%,:42%,:2,0,1,0,0,0"}]},{"id":"2","name":"Na Li","fname":"Na","lname":"Li","key":[{"data":"145:5:60%,75%,53%,0%,0%,0%:60%,75%,53%,0%,0%,0%:52%,:52%,:1,1,1,0,0,0"},{"data":"52:5:43%,63%,33%,0%,0%,0%:43%,63%,33%,0%,0%,0%:35%,:35%,:1,1,0,0,0,0"},{"data":"19:5:64%,77%,59%,0%,0%,0%:64%,77%,59%,0%,0%,0%:65%,:65%,:2,1,0,0,0,0"}]}]}