[{"ElapsedTime":"0:00:00","SetNo":"1","P1GamesWon":"0","P2GamesWon":"0","SetWinner":"0","GameNo":"1","GameWinner":"0","PointNumber":"1","PointWinner":"2","PointServer":"1","Speed_KMH":"0","P1Score":"0","P2Score":"15","PointTrack":"-1","SetTrack":"-1","P1PointsWon":"0","P2PointsWon":"0","Ace":"0","Winner":"0","DoubleFault":"1","UnforcedError":"1","NetPoint":"0","BreakPoint":"0","BreakPointWon":"0","History":"15000","Speed_MPH":"0","ServeIndicator":"1"},{"ElapsedTime":"0:00:32","SetNo":"1","P1GamesWon":"0","P2GamesWon":"0","SetWinner":"0","GameNo":"1","GameWinner":"0","PointNumber":"2","PointWinner":"2","PointServer":"1","Speed_KMH":"201","P1Score":"0","P2Score":"30","PointTrack":"-2","SetTrack":"-2","P1PointsWon":"0","P2PointsWon":"0","Ace":"0","Winner":"2","DoubleFault":"0","UnforcedError":"0","NetPoint":"0","BreakPoint":"0","BreakPointWon":"0","History":"22010","Speed_MPH":"124","ServeIndicator":"1"},{"ElapsedTime":"0:00:57","SetNo":"1","P1GamesWon":"0","P2GamesWon":"0","SetWinner":"0","GameNo":"1","GameWinner":"0","PointNumber":"3","PointWinner":"2","PointServer":"1","Speed_KMH":"0","P1Score":"0","P2Score":"40","PointTrack":"-3","SetTrack":"-3","P1PointsWon":"0","P2PointsWon":"0","Ace":"0","Winner":"0","DoubleFault":"1","UnforcedError":"1","NetPoint":"0","BreakPoint":"0","BreakPointWon":"0","History":"15000","Speed_MPH":"0","ServeIndicator":"1"},{"ElapsedTime":"0:01:39","SetNo":"1","P1GamesWon":"0","P2GamesWon":"0","SetWinner":"0","GameNo":"1","GameWinner":"0","PointNumber":"4","PointWinner":"1","PointServer":"1","Speed_KMH":"173","P1Score":"15","P2Score":"40","PointTrack":"-2","SetTrack":"-2","P1PointsWon":"0","P2PointsWon":"0","Ace":"0","Winner":"1","DoubleFault":"0","UnforcedError":"0","NetPoint":"0","BreakPoint":"2","BreakPointWon":"0","History":"12510","Speed_MPH":"107","ServeIndicator":"1"},{"ElapsedTime":"0:02:03","SetNo":"1","P1GamesWon":"0","P2GamesWon":"1","SetWinner":"0","GameNo":"1","GameWinner":"2","PointNumber":"5","PointWinner":"2","PointServer":"1","Speed_KMH":"187","P1Score":"0","P2Score":"0","PointTrack":"-8","SetTrack":"-8","P1PointsWon":"0","P2PointsWon":"0","Ace":"0","Winner":"0","DoubleFault":"0","UnforcedError":"1","NetPoint":"0","BreakPoint":"2","BreakPointWon":"2","History":"11022","Speed_MPH":"116","ServeIndicator":"2"},{"ElapsedTime":"0:02:58","SetNo":"1","P1GamesWon":"0","P2GamesWon":"1","SetWinner":"0","GameNo":"2","GameWinner":"0","PointNumber":"6","PointWinner":"2","PointServer":"2","Speed_KMH":"168","P1Score":"0","P2Score":"15","PointTrack":"-9","SetTrack":"-9","P1PointsWon":"0","P2PointsWon":"0","Ace":"0","Winner":"0","DoubleFault":"0","UnforcedError":"0","NetPoint":"0","BreakPoint":"0","BreakPointWon":"0","History":"11030","Speed_MPH":"104","ServeIndicator":"2"},{"ElapsedTime":"0:03:35","SetNo":"1","P1GamesWon":"0","P2GamesWon":"1","SetWinner":"0","GameNo":"2","GameWinner":"0","PointNumber":"7","PointWinner":"2","PointServer":"2","Speed_KMH":"200","P1Score":"0","P2Score":"30","PointTrack":"-10","SetTrack":"-10","P1PointsWon":"0","P2PointsWon":"0","Ace":"0","Winner":"2","DoubleFault":"0","UnforcedError":"0","NetPoint":"0","BreakPoint":"0","BreakPointWon":"0","History":"21410","Speed_MPH":"124","ServeIndicator":"2"},{"ElapsedTime":"0:03:55","SetNo":"1","P1GamesWon":"0","P2GamesWon":"1","SetWinner":"0","GameNo":"2","GameWinner":"0","PointNumber":"8","PointWinner":"2","PointServer":"2","Speed_KMH":"208","P1Score":"0","P2Score":"40","PointTrack":"-11","SetTrack":"-11","P1PointsWon":"0","P2PointsWon":"0","Ace":"2","Winner":"2","DoubleFault":"0","UnforcedError":"0","NetPoint":"0","BreakPoint":"0","BreakPointWon":"0","History":"23000","Speed_MPH":"129","ServeIndicator":"2"},{"ElapsedTime":"0:04:15","SetNo":"1","P1GamesWon":"0","P2GamesWon":"2","SetWinner":"0","GameNo":"2","GameWinner":"2","PointNumber":"9","PointWinner":"2","PointServer":"2","Speed_KMH":"189","P1Score":"0","P2Score":"0","PointTrack":"-12","SetTrack":"-12","P1PointsWon":"0","P2PointsWon":"0","Ace":"0","Winner":"0","DoubleFault":"0","UnforcedError":"0","NetPoint":"0","BreakPoint":"0","BreakPointWon":"0","History":"11032","Speed_MPH":"117","ServeIndicator":"1"},{"ElapsedTime":"0:04:46","SetNo":"1","P1GamesWon":"0","P2GamesWon":"2","SetWinner":"0","GameNo":"3","GameWinner":"0","PointNumber":"10","PointWinner":"1","PointServer":"1","Speed_KMH":"176","P1Score":"15","P2Score":"0","PointTrack":"-11","SetTrack":"-11","P1PointsWon":"0","P2PointsWon":"0","Ace":"0","Winner":"0","DoubleFault":"0","UnforcedError":"0","NetPoint":"0","BreakPoint":"0","BreakPointWon":"0","History":"21030","Speed_MPH":"109","ServeIndicator":"1"},{"ElapsedTime":"0:05:22","SetNo":"1","P1GamesWon":"0","P2GamesWon":"2","SetWinner":"0","GameNo":"3","GameWinner":"0","PointNumber":"11","PointWinner":"1","PointServer":"1","Speed_KMH":"187","P1Score":"30","P2Score":"0","PointTrack":"-10","SetTrack":"-10","P1PointsWon":"0","P2PointsWon":"0","Ace":"1","Winner":"1","DoubleFault":"0","UnforcedError":"0","NetPoint":"0","BreakPoint":"0","BreakPointWon":"0","History":"13000","Speed_MPH":"116","ServeIndicator":"1"},{"ElapsedTime":"0:05:43","SetNo":"1","P1GamesWon":"0","P2GamesWon":"2","SetWinner":"0","GameNo":"3","GameWinner":"0","PointNumber":"12","PointWinner":"1","PointServer":"1","Speed_KMH":"182","P1Score":"40","P2Score":"0","PointTrack":"-9","SetTrack":"-9","P1PointsWon":"0","P2PointsWon":"0","Ace":"1","Winner":"1","DoubleFault":"0","UnforcedError":"0","NetPoint":"0","BreakPoint":"0","BreakPointWon":"0","History":"13000","Speed_MPH":"113","ServeIndicator":"1"},{"ElapsedTime":"0:06:05","SetNo":"1","P1GamesWon":"1","P2GamesWon":"2","SetWinner":"0","GameNo":"3","GameWinner":"1","PointNumber":"13","PointWinner":"1","PointServer":"1","Speed_KMH":"157","P1Score":"0","P2Score":"0","PointTrack":"-8","SetTrack":"-8","P1PointsWon":"0","P2PointsWon":"0","Ace":"0","Winner":"1","DoubleFault":"0","UnforcedError":"0","NetPoint":"0","BreakPoint":"0","BreakPointWon":"0","History":"12412","Speed_MPH":"97","ServeIndicator":"2"},{"ElapsedTime":"0:07:32","SetNo":"1","P1GamesWon":"1","P2GamesWon":"2","SetWinner":"0","GameNo":"4","GameWinner":"0","PointNumber":"14","PointWinner":"2","PointServer":"2","Speed_KMH":"145","P1Score":"0","P2Score":"15","PointTrack":"-9","SetTrack":"-9","P1PointsWon":"0","P2PointsWon":"0","Ace":"0","Winner":"0","DoubleFault":"0","UnforcedError":"0","NetPoint":"0","BreakPoint":"0","BreakPointWon":"0","History":"11030","Speed_MPH":"90","ServeIndicator":"2"},{"ElapsedTime":"0:08:09","SetNo":"1","P1GamesWon":"1","P2GamesWon":"2","SetWinner":"0","GameNo":"4","GameWinner":"0","PointNumber":"15","PointWinner":"2","PointServer":"2","Speed_KMH":"178","P1Score":"0","P2Score":"30","PointTrack":"-10","SetTrack":"-10","P1PointsWon":"0","P2PointsWon":"0","Ace":"0","Winner":"0","DoubleFault":"0","UnforcedError":"0","NetPoint":"0","BreakPoint":"0","BreakPointWon":"0","History":"11030","Speed_MPH":"110","ServeIndicator":"2"},{"ElapsedTime":"0:08:30","SetNo":"1","P1GamesWon":"1","P2GamesWon":"2","SetWinner":"0","GameNo":"4","GameWinner":"0","PointNumber":"16","PointWinner":"2","PointServer":"2","Speed_KMH":"184","P1Score":"0","P2Score":"40","PointTrack":"-11","SetTrack":"-11","P1PointsWon":"0","P2PointsWon":"0","Ace":"2","Winner":"2","DoubleFault":"0","UnforcedError":"0","NetPoint":"0","BreakPoint":"0","BreakPointWon":"0","History":"23000","Speed_MPH":"114","ServeIndicator":"2"},{"ElapsedTime":"0:08:51","SetNo":"1","P1GamesWon":"1","P2GamesWon":"3","SetWinner":"0","GameNo":"4","GameWinner":"2","PointNumber":"17","PointWinner":"2","PointServer":"2","Speed_KMH":"161","P1Score":"0","P2Score":"0","PointTrack":"-12","SetTrack":"-12","P1PointsWon":"0","P2PointsWon":"0","Ace":"0","Winner":"2","DoubleFault":"0","UnforcedError":"0","NetPoint":"0","BreakPoint":"0","BreakPointWon":"0","History":"21412","Speed_MPH":"100","ServeIndicator":"1"},{"ElapsedTime":"0:09:27","SetNo":"1","P1GamesWon":"1","P2GamesWon":"3","SetWinner":"0","GameNo":"5","GameWinner":"0","PointNumber":"18","PointWinner":"1","PointServer":"1","Speed_KMH":"189","P1Score":"15","P2Score":"0","PointTrack":"-11","SetTrack":"-11","P1PointsWon":"0","P2PointsWon":"0","Ace":"0","Winner":"1","DoubleFault":"0","UnforcedError":"0","NetPoint":"0","BreakPoint":"0","BreakPointWon":"0","History":"12410","Speed_MPH":"117","ServeIndicator":"1"},{"ElapsedTime":"0:09:52","SetNo":"1","P1GamesWon":"1","P2GamesWon":"3","SetWinner":"0","GameNo":"5","GameWinner":"0","PointNumber":"19","PointWinner":"1","PointServer":"1","Speed_KMH":"180","P1Score":"30","P2Score":"0","PointTrack":"-10","SetTrack":"-10","P1PointsWon":"0","P2PointsWon":"0","Ace":"0","Winner":"1","DoubleFault":"0","UnforcedError":"0","NetPoint":"0","BreakPoint":"0","BreakPointWon":"0","History":"11410","Speed_MPH":"111","ServeIndicator":"1"},{"ElapsedTime":"0:10:13","SetNo":"1","P1GamesWon":"1","P2GamesWon":"3","SetWinner":"0","GameNo":"5","GameWinner":"0","PointNumber":"20","PointWinner":"2","PointServer":"1","Speed_KMH":"192","P1Score":"30","P2Score":"15","PointTrack":"-11","SetTrack":"-11","P1PointsWon":"0","P2PointsWon":"0","Ace":"0","Winner":"2","DoubleFault":"0","UnforcedError":"0","NetPoint":"0","BreakPoint":"0","BreakPointWon":"0","History":"21010","Speed_MPH":"119","ServeIndicator":"1"},{"ElapsedTime":"0:10:35","SetNo":"1","P1GamesWon":"1","P2GamesWon":"3","SetWinner":"0","GameNo":"5","GameWinner":"0","PointNumber":"21","PointWinner":"1","PointServer":"1","Speed_KMH":"148","P1Score":"40","P2Score":"15","PointTrack":"-10","SetTrack":"-10","P1PointsWon":"0","P2PointsWon":"0","Ace":"0","Winner":"0","DoubleFault":"0","UnforcedError":"0","NetPoint":"0","BreakPoint":"0","BreakPointWon":"0","History":"22030","Speed_MPH":"92","ServeIndicator":"1"},{"ElapsedTime":"0:11:11","SetNo":"1","P1GamesWon":"2","P2GamesWon":"3","SetWinner":"0","GameNo":"5","GameWinner":"1","PointNumber":"22","PointWinner":"1","PointServer":"1","Speed_KMH":"193","P1Score":"0","P2Score":"0","PointTrack":"-8","SetTrack":"-8","P1PointsWon":"0","P2PointsWon":"0","Ace":"0","Winner":"0","DoubleFault":"0","UnforcedError":"0","NetPoint":"0","BreakPoint":"0","BreakPointWon":"0","History":"21032","Speed_MPH":"120","ServeIndicator":"2"},{"ElapsedTime":"0:12:32","SetNo":"1","P1GamesWon":"2","P2GamesWon":"3","SetWinner":"0","GameNo":"6","GameWinner":"0","PointNumber":"23","PointWinner":"2","PointServer":"2","Speed_KMH":"179","P1Score":"0","P2Score":"15","PointTrack":"-9","SetTrack":"-9","P1PointsWon":"0","P2PointsWon":"0","Ace":"0","Winner":"2","DoubleFault":"0","UnforcedError":"0","NetPoint":"0","BreakPoint":"0","BreakPointWon":"0","History":"21510","Speed_MPH":"111","ServeIndicator":"2"},{"ElapsedTime":"0:13:09","SetNo":"1","P1GamesWon":"2","P2GamesWon":"3","SetWinner":"0","GameNo":"6","GameWinner":"0","PointNumber":"24","PointWinner":"1","PointServer":"2","Speed_KMH":"161","P1Score":"15","P2Score":"15","PointTrack":"-8","SetTrack":"-8","P1PointsWon":"0","P2PointsWon":"0","Ace":"0","Winner":"0","DoubleFault":"0","UnforcedError":"0","NetPoint":"0","BreakPoint":"0","BreakPointWon":"0","History":"22430","Speed_MPH":"100","ServeIndicator":"2"},{"ElapsedTime":"0:13:47","SetNo":"1","P1GamesWon":"2","P2GamesWon":"3","SetWinner":"0","GameNo":"6","GameWinner":"0","PointNumber":"25","PointWinner":"2","PointServer":"2","Speed_KMH":"189","P1Score":"15","P2Score":"30","PointTrack":"-9","SetTrack":"-9","P1PointsWon":"0","P2PointsWon":"0","Ace":"0","Winner":"0","DoubleFault":"0","UnforcedError":"0","NetPoint":"0","BreakPoint":"0","BreakPointWon":"0","History":"11030","Speed_MPH":"117","ServeIndicator":"2"},{"ElapsedTime":"0:14:07","SetNo":"1","P1GamesWon":"2","P2GamesWon":"3","SetWinner":"0","GameNo":"6","GameWinner":"0","PointNumber":"26","PointWinner":"2","PointServer":"2","Speed_KMH":"198","P1Score":"15","P2Score":"40","PointTrack":"-10","SetTrack":"-10","P1PointsWon":"0","P2PointsWon":"0","Ace":"0","Winner":"0","DoubleFault":"0","UnforcedError":"0","NetPoint":"0","BreakPoint":"0","BreakPointWon":"0","History":"11030","Speed_MPH":"123","ServeIndicator":"2"},{"ElapsedTime":"0:14:25","SetNo":"1","P1GamesWon":"2","P2GamesWon":"4","SetWinner":"0","GameNo":"6","GameWinner":"2","PointNumber":"27","PointWinner":"2","PointServer":"2","Speed_KMH":"205","P1Score":"0","P2Score":"0","PointTrack":"-12","SetTrack":"-12","P1PointsWon":"0","P2PointsWon":"0","Ace":"0","Winner":"0","DoubleFault":"0","UnforcedError":"0","NetPoint":"0","BreakPoint":"0","BreakPointWon":"0","History":"11032","Speed_MPH":"127","ServeIndicator":"1"},{"ElapsedTime":"0:14:56","SetNo":"1","P1GamesWon":"2","P2GamesWon":"4","SetWinner":"0","GameNo":"7","GameWinner":"0","PointNumber":"28","PointWinner":"1","PointServer":"1","Speed_KMH":"180","P1Score":"15","P2Score":"0","PointTrack":"-11","SetTrack":"-11","P1PointsWon":"0","P2PointsWon":"0","Ace":"0","Winner":"0","DoubleFault":"0","UnforcedError":"0","NetPoint":"0","BreakPoint":"0","BreakPointWon":"0","History":"21030","Speed_MPH":"111","ServeIndicator":"1"},{"ElapsedTime":"0:15:21","SetNo":"1","P1GamesWon":"2","P2GamesWon":"4","SetWinner":"0","GameNo":"7","GameWinner":"0","PointNumber":"29","PointWinner":"1","PointServer":"1","Speed_KMH":"150","P1Score":"30","P2Score":"0","PointTrack":"-10","SetTrack":"-10","P1PointsWon":"0","P2PointsWon":"0","Ace":"0","Winner":"0","DoubleFault":"0","UnforcedError":"0","NetPoint":"0","BreakPoint":"0","BreakPointWon":"0","History":"21030","Speed_MPH":"93","ServeIndicator":"1"},{"ElapsedTime":"0:15:55","SetNo":"1","P1GamesWon":"2","P2GamesWon":"4","SetWinner":"0","GameNo":"7","GameWinner":"0","PointNumber":"30","PointWinner":"2","PointServer":"1","Speed_KMH":"0","P1Score":"30","P2Score":"15","PointTrack":"-11","SetTrack":"-11","P1PointsWon":"0","P2PointsWon":"0","Ace":"0","Winner":"0","DoubleFault":"1","UnforcedError":"1","NetPoint":"0","BreakPoint":"0","BreakPointWon":"0","History":"15000","Speed_MPH":"0","ServeIndicator":"1"},{"ElapsedTime":"0:16:31","SetNo":"1","P1GamesWon":"2","P2GamesWon":"4","SetWinner":"0","GameNo":"7","GameWinner":"0","PointNumber":"31","PointWinner":"2","PointServer":"1","Speed_KMH":"156","P1Score":"30","P2Score":"30","PointTrack":"-12","SetTrack":"-12","P1PointsWon":"0","P2PointsWon":"0","Ace":"0","Winner":"2","DoubleFault":"0","UnforcedError":"0","NetPoint":"0","BreakPoint":"0","BreakPointWon":"0","History":"21010","Speed_MPH":"97","ServeIndicator":"1"},{"ElapsedTime":"0:17:06","SetNo":"1","P1GamesWon":"2","P2GamesWon":"4","SetWinner":"0","GameNo":"7","GameWinner":"0","PointNumber":"32","PointWinner":"2","PointServer":"1","Speed_KMH":"183","P1Score":"30","P2Score":"40","PointTrack":"-13","SetTrack":"-13","P1PointsWon":"0","P2PointsWon":"0","Ace":"0","Winner":"0","DoubleFault":"0","UnforcedError":"1","NetPoint":"0","BreakPoint":"0","BreakPointWon":"0","History":"11420","Speed_MPH":"113","ServeIndicator":"1"},{"ElapsedTime":"0:17:32","SetNo":"1","P1GamesWon":"2","P2GamesWon":"5","SetWinner":"0","GameNo":"7","GameWinner":"2","PointNumber":"33","PointWinner":"2","PointServer":"1","Speed_KMH":"183","P1Score":"0","P2Score":"0","PointTrack":"-16","SetTrack":"-16","P1PointsWon":"0","P2PointsWon":"0","Ace":"0","Winner":"0","DoubleFault":"0","UnforcedError":"1","NetPoint":"0","BreakPoint":"2","BreakPointWon":"2","History":"12022","Speed_MPH":"113","ServeIndicator":"2"},{"ElapsedTime":"0:18:59","SetNo":"1","P1GamesWon":"2","P2GamesWon":"5","SetWinner":"0","GameNo":"8","GameWinner":"0","PointNumber":"34","PointWinner":"1","PointServer":"2","Speed_KMH":"0","P1Score":"15","P2Score":"0","PointTrack":"-15","SetTrack":"-15","P1PointsWon":"0","P2PointsWon":"0","Ace":"0","Winner":"0","DoubleFault":"2","UnforcedError":"2","NetPoint":"0","BreakPoint":"0","BreakPointWon":"0","History":"25000","Speed_MPH":"0","ServeIndicator":"2"},{"ElapsedTime":"0:19:32","SetNo":"1","P1GamesWon":"2","P2GamesWon":"5","SetWinner":"0","GameNo":"8","GameWinner":"0","PointNumber":"35","PointWinner":"2","PointServer":"2","Speed_KMH":"133","P1Score":"15","P2Score":"15","PointTrack":"-16","SetTrack":"-16","P1PointsWon":"0","P2PointsWon":"0","Ace":"0","Winner":"0","DoubleFault":"0","UnforcedError":"1","NetPoint":"0","BreakPoint":"0","BreakPointWon":"0","History":"11020","Speed_MPH":"82","ServeIndicator":"2"},{"ElapsedTime":"0:20:09","SetNo":"1","P1GamesWon":"2","P2GamesWon":"5","SetWinner":"0","GameNo":"8","GameWinner":"0","PointNumber":"36","PointWinner":"2","PointServer":"2","Speed_KMH":"184","P1Score":"15","P2Score":"30","PointTrack":"-17","SetTrack":"-17","P1PointsWon":"0","P2PointsWon":"0","Ace":"2","Winner":"2","DoubleFault":"0","UnforcedError":"0","NetPoint":"0","BreakPoint":"0","BreakPointWon":"0","History":"23000","Speed_MPH":"114","ServeIndicator":"2"},{"ElapsedTime":"0:20:30","SetNo":"1","P1GamesWon":"2","P2GamesWon":"5","SetWinner":"0","GameNo":"8","GameWinner":"0","PointNumber":"37","PointWinner":"2","PointServer":"2","Speed_KMH":"175","P1Score":"15","P2Score":"40","PointTrack":"-18","SetTrack":"-18","P1PointsWon":"0","P2PointsWon":"0","Ace":"0","Winner":"0","DoubleFault":"0","UnforcedError":"0","NetPoint":"0","BreakPoint":"0","BreakPointWon":"0","History":"11030","Speed_MPH":"108","ServeIndicator":"2"},{"ElapsedTime":"0:20:52","SetNo":"1","P1GamesWon":"2","P2GamesWon":"6","SetWinner":"2","GameNo":"8","GameWinner":"2","PointNumber":"38","PointWinner":"2","PointServer":"2","Speed_KMH":"147","P1Score":"0","P2Score":"0","PointTrack":"-20","SetTrack":"-24","P1PointsWon":"0","P2PointsWon":"0","Ace":"0","Winner":"0","DoubleFault":"0","UnforcedError":"0","NetPoint":"0","BreakPoint":"0","BreakPointWon":"0","History":"12033","Speed_MPH":"91","ServeIndicator":"1"},{"ElapsedTime":"0:22:44","SetNo":"2","P1GamesWon":"0","P2GamesWon":"0","SetWinner":"0","GameNo":"1","GameWinner":"0","PointNumber":"39","PointWinner":"1","PointServer":"1","Speed_KMH":"186","P1Score":"15","P2Score":"0","PointTrack":"1","SetTrack":"-23","P1PointsWon":"0","P2PointsWon":"0","Ace":"0","Winner":"0","DoubleFault":"0","UnforcedError":"0","NetPoint":"0","BreakPoint":"0","BreakPointWon":"0","History":"21030","Speed_MPH":"115","ServeIndicator":"1"},{"ElapsedTime":"0:23:07","SetNo":"2","P1GamesWon":"0","P2GamesWon":"0","SetWinner":"0","GameNo":"1","GameWinner":"0","PointNumber":"40","PointWinner":"2","PointServer":"1","Speed_KMH":"157","P1Score":"15","P2Score":"15","PointTrack":"0","SetTrack":"-24","P1PointsWon":"0","P2PointsWon":"0","Ace":"0","Winner":"0","DoubleFault":"0","UnforcedError":"0","NetPoint":"0","BreakPoint":"0","BreakPointWon":"0","History":"12430","Speed_MPH":"97","ServeIndicator":"1"},{"ElapsedTime":"0:23:41","SetNo":"2","P1GamesWon":"0","P2GamesWon":"0","SetWinner":"0","GameNo":"1","GameWinner":"0","PointNumber":"41","PointWinner":"2","PointServer":"1","Speed_KMH":"0","P1Score":"15","P2Score":"30","PointTrack":"-1","SetTrack":"-25","P1PointsWon":"0","P2PointsWon":"0","Ace":"0","Winner":"0","DoubleFault":"1","UnforcedError":"1","NetPoint":"0","BreakPoint":"0","BreakPointWon":"0","History":"15000","Speed_MPH":"0","ServeIndicator":"1"},{"ElapsedTime":"0:24:15","SetNo":"2","P1GamesWon":"0","P2GamesWon":"0","SetWinner":"0","GameNo":"1","GameWinner":"0","PointNumber":"42","PointWinner":"1","PointServer":"1","Speed_KMH":"175","P1Score":"30","P2Score":"30","PointTrack":"0","SetTrack":"-24","P1PointsWon":"0","P2PointsWon":"0","Ace":"0","Winner":"0","DoubleFault":"0","UnforcedError":"0","NetPoint":"0","BreakPoint":"0","BreakPointWon":"0","History":"22030","Speed_MPH":"108","ServeIndicator":"1"},{"ElapsedTime":"0:24:37","SetNo":"2","P1GamesWon":"0","P2GamesWon":"0","SetWinner":"0","GameNo":"1","GameWinner":"0","PointNumber":"43","PointWinner":"1","PointServer":"1","Speed_KMH":"199","P1Score":"40","P2Score":"30","PointTrack":"1","SetTrack":"-23","P1PointsWon":"0","P2PointsWon":"0","Ace":"0","Winner":"0","DoubleFault":"0","UnforcedError":"0","NetPoint":"0","BreakPoint":"0","BreakPointWon":"0","History":"21030","Speed_MPH":"123","ServeIndicator":"1"},{"ElapsedTime":"0:24:59","SetNo":"2","P1GamesWon":"1","P2GamesWon":"0","SetWinner":"0","GameNo":"1","GameWinner":"1","PointNumber":"44","PointWinner":"1","PointServer":"1","Speed_KMH":"160","P1Score":"0","P2Score":"0","PointTrack":"4","SetTrack":"-20","P1PointsWon":"0","P2PointsWon":"0","Ace":"0","Winner":"0","DoubleFault":"0","UnforcedError":"2","NetPoint":"0","BreakPoint":"0","BreakPointWon":"0","History":"22022","Speed_MPH":"99","ServeIndicator":"2"},{"ElapsedTime":"0:26:00","SetNo":"2","P1GamesWon":"1","P2GamesWon":"0","SetWinner":"0","GameNo":"2","GameWinner":"0","PointNumber":"45","PointWinner":"1","PointServer":"2","Speed_KMH":"163","P1Score":"15","P2Score":"0","PointTrack":"5","SetTrack":"-19","P1PointsWon":"0","P2PointsWon":"0","Ace":"0","Winner":"0","DoubleFault":"0","UnforcedError":"0","NetPoint":"0","BreakPoint":"0","BreakPointWon":"0","History":"21430","Speed_MPH":"101","ServeIndicator":"2"},{"ElapsedTime":"0:26:55","SetNo":"2","P1GamesWon":"1","P2GamesWon":"0","SetWinner":"0","GameNo":"2","GameWinner":"0","PointNumber":"46","PointWinner":"2","PointServer":"2","Speed_KMH":"144","P1Score":"15","P2Score":"15","PointTrack":"4","SetTrack":"-20","P1PointsWon":"0","P2PointsWon":"0","Ace":"0","Winner":"0","DoubleFault":"0","UnforcedError":"0","NetPoint":"0","BreakPoint":"0","BreakPointWon":"0","History":"11030","Speed_MPH":"89","ServeIndicator":"2"},{"ElapsedTime":"0:27:32","SetNo":"2","P1GamesWon":"1","P2GamesWon":"0","SetWinner":"0","GameNo":"2","GameWinner":"0","PointNumber":"47","PointWinner":"2","PointServer":"2","Speed_KMH":"198","P1Score":"15","P2Score":"30","PointTrack":"3","SetTrack":"-21","P1PointsWon":"0","P2PointsWon":"0","Ace":"2","Winner":"2","DoubleFault":"0","UnforcedError":"0","NetPoint":"0","BreakPoint":"0","BreakPointWon":"0","History":"23000","Speed_MPH":"123","ServeIndicator":"2"},{"ElapsedTime":"0:27:52","SetNo":"2","P1GamesWon":"1","P2GamesWon":"0","SetWinner":"0","GameNo":"2","GameWinner":"0","PointNumber":"48","PointWinner":"2","PointServer":"2","Speed_KMH":"207","P1Score":"15","P2Score":"40","PointTrack":"2","SetTrack":"-22","P1PointsWon":"0","P2PointsWon":"0","Ace":"2","Winner":"2","DoubleFault":"0","UnforcedError":"0","NetPoint":"0","BreakPoint":"0","BreakPointWon":"0","History":"23000","Speed_MPH":"128","ServeIndicator":"2"},{"ElapsedTime":"0:28:19","SetNo":"2","P1GamesWon":"1","P2GamesWon":"1","SetWinner":"0","GameNo":"2","GameWinner":"2","PointNumber":"49","PointWinner":"2","PointServer":"2","Speed_KMH":"178","P1Score":"0","P2Score":"0","PointTrack":"0","SetTrack":"-24","P1PointsWon":"0","P2PointsWon":"0","Ace":"0","Winner":"2","DoubleFault":"0","UnforcedError":"0","NetPoint":"0","BreakPoint":"0","BreakPointWon":"0","History":"21512","Speed_MPH":"110","ServeIndicator":"1"},{"ElapsedTime":"0:28:51","SetNo":"2","P1GamesWon":"1","P2GamesWon":"1","SetWinner":"0","GameNo":"3","GameWinner":"0","PointNumber":"50","PointWinner":"1","PointServer":"1","Speed_KMH":"166","P1Score":"15","P2Score":"0","PointTrack":"1","SetTrack":"-23","P1PointsWon":"0","P2PointsWon":"0","Ace":"0","Winner":"1","DoubleFault":"0","UnforcedError":"0","NetPoint":"0","BreakPoint":"0","BreakPointWon":"0","History":"11410","Speed_MPH":"103","ServeIndicator":"1"},{"ElapsedTime":"0:29:11","SetNo":"2","P1GamesWon":"1","P2GamesWon":"1","SetWinner":"0","GameNo":"3","GameWinner":"0","PointNumber":"51","PointWinner":"2","PointServer":"1","Speed_KMH":"150","P1Score":"15","P2Score":"15","PointTrack":"0","SetTrack":"-24","P1PointsWon":"0","P2PointsWon":"0","Ace":"0","Winner":"2","DoubleFault":"0","UnforcedError":"0","NetPoint":"0","BreakPoint":"0","BreakPointWon":"0","History":"22410","Speed_MPH":"93","ServeIndicator":"1"},{"ElapsedTime":"0:30:18","SetNo":"2","P1GamesWon":"1","P2GamesWon":"1","SetWinner":"0","GameNo":"3","GameWinner":"0","PointNumber":"52","PointWinner":"1","PointServer":"1","Speed_KMH":"157","P1Score":"30","P2Score":"15","PointTrack":"1","SetTrack":"-23","P1PointsWon":"0","P2PointsWon":"0","Ace":"0","Winner":"1","DoubleFault":"0","UnforcedError":"0","NetPoint":"0","BreakPoint":"0","BreakPointWon":"0","History":"12410","Speed_MPH":"97","ServeIndicator":"1"},{"ElapsedTime":"0:31:00","SetNo":"2","P1GamesWon":"1","P2GamesWon":"1","SetWinner":"0","GameNo":"3","GameWinner":"0","PointNumber":"53","PointWinner":"1","PointServer":"1","Speed_KMH":"189","P1Score":"40","P2Score":"15","PointTrack":"2","SetTrack":"-22","P1PointsWon":"0","P2PointsWon":"0","Ace":"0","Winner":"1","DoubleFault":"0","UnforcedError":"0","NetPoint":"0","BreakPoint":"0","BreakPointWon":"0","History":"11510","Speed_MPH":"117","ServeIndicator":"1"},{"ElapsedTime":"0:31:20","SetNo":"2","P1GamesWon":"2","P2GamesWon":"1","SetWinner":"0","GameNo":"3","GameWinner":"1","PointNumber":"54","PointWinner":"1","PointServer":"1","Speed_KMH":"145","P1Score":"0","P2Score":"0","PointTrack":"4","SetTrack":"-20","P1PointsWon":"0","P2PointsWon":"0","Ace":"0","Winner":"0","DoubleFault":"0","UnforcedError":"0","NetPoint":"0","BreakPoint":"0","BreakPointWon":"0","History":"22032","Speed_MPH":"90","ServeIndicator":"2"},{"ElapsedTime":"0:32:51","SetNo":"2","P1GamesWon":"2","P2GamesWon":"1","SetWinner":"0","GameNo":"4","GameWinner":"0","PointNumber":"55","PointWinner":"2","PointServer":"2","Speed_KMH":"177","P1Score":"0","P2Score":"15","PointTrack":"3","SetTrack":"-21","P1PointsWon":"0","P2PointsWon":"0","Ace":"0","Winner":"0","DoubleFault":"0","UnforcedError":"0","NetPoint":"0","BreakPoint":"0","BreakPointWon":"0","History":"12030","Speed_MPH":"110","ServeIndicator":"2"},{"ElapsedTime":"0:33:10","SetNo":"2","P1GamesWon":"2","P2GamesWon":"1","SetWinner":"0","GameNo":"4","GameWinner":"0","PointNumber":"56","PointWinner":"1","PointServer":"2","Speed_KMH":"160","P1Score":"15","P2Score":"15","PointTrack":"4","SetTrack":"-20","P1PointsWon":"0","P2PointsWon":"0","Ace":"0","Winner":"0","DoubleFault":"0","UnforcedError":"0","NetPoint":"0","BreakPoint":"0","BreakPointWon":"0","History":"21430","Speed_MPH":"99","ServeIndicator":"2"},{"ElapsedTime":"0:33:40","SetNo":"2","P1GamesWon":"2","P2GamesWon":"1","SetWinner":"0","GameNo":"4","GameWinner":"0","PointNumber":"57","PointWinner":"2","PointServer":"2","Speed_KMH":"185","P1Score":"15","P2Score":"30","PointTrack":"3","SetTrack":"-21","P1PointsWon":"0","P2PointsWon":"0","Ace":"0","Winner":"2","DoubleFault":"0","UnforcedError":"0","NetPoint":"0","BreakPoint":"0","BreakPointWon":"0","History":"24000","Speed_MPH":"115","ServeIndicator":"2"},{"ElapsedTime":"0:34:01","SetNo":"2","P1GamesWon":"2","P2GamesWon":"1","SetWinner":"0","GameNo":"4","GameWinner":"0","PointNumber":"58","PointWinner":"2","PointServer":"2","Speed_KMH":"154","P1Score":"15","P2Score":"40","PointTrack":"2","SetTrack":"-22","P1PointsWon":"0","P2PointsWon":"0","Ace":"0","Winner":"0","DoubleFault":"0","UnforcedError":"0","NetPoint":"0","BreakPoint":"0","BreakPointWon":"0","History":"11030","Speed_MPH":"95","ServeIndicator":"2"},{"ElapsedTime":"0:34:45","SetNo":"2","P1GamesWon":"2","P2GamesWon":"2","SetWinner":"0","GameNo":"4","GameWinner":"2","PointNumber":"59","PointWinner":"2","PointServer":"2","Speed_KMH":"143","P1Score":"0","P2Score":"0","PointTrack":"0","SetTrack":"-24","P1PointsWon":"0","P2PointsWon":"0","Ace":"0","Winner":"0","DoubleFault":"0","UnforcedError":"0","NetPoint":"0","BreakPoint":"0","BreakPointWon":"0","History":"12032","Speed_MPH":"88","ServeIndicator":"1"},{"ElapsedTime":"0:35:43","SetNo":"2","P1GamesWon":"2","P2GamesWon":"2","SetWinner":"0","GameNo":"5","GameWinner":"0","PointNumber":"60","PointWinner":"2","PointServer":"1","Speed_KMH":"0","P1Score":"0","P2Score":"15","PointTrack":"-1","SetTrack":"-25","P1PointsWon":"0","P2PointsWon":"0","Ace":"0","Winner":"0","DoubleFault":"1","UnforcedError":"1","NetPoint":"0","BreakPoint":"0","BreakPointWon":"0","History":"15000","Speed_MPH":"0","ServeIndicator":"1"},{"ElapsedTime":"0:36:17","SetNo":"2","P1GamesWon":"2","P2GamesWon":"2","SetWinner":"0","GameNo":"5","GameWinner":"0","PointNumber":"61","PointWinner":"1","PointServer":"1","Speed_KMH":"199","P1Score":"15","P2Score":"15","PointTrack":"0","SetTrack":"-24","P1PointsWon":"0","P2PointsWon":"0","Ace":"0","Winner":"1","DoubleFault":"0","UnforcedError":"0","NetPoint":"0","BreakPoint":"0","BreakPointWon":"0","History":"12410","Speed_MPH":"123","ServeIndicator":"1"},{"ElapsedTime":"0:36:57","SetNo":"2","P1GamesWon":"2","P2GamesWon":"2","SetWinner":"0","GameNo":"5","GameWinner":"0","PointNumber":"62","PointWinner":"1","PointServer":"1","Speed_KMH":"206","P1Score":"30","P2Score":"15","PointTrack":"1","SetTrack":"-23","P1PointsWon":"0","P2PointsWon":"0","Ace":"0","Winner":"0","DoubleFault":"0","UnforcedError":"0","NetPoint":"0","BreakPoint":"0","BreakPointWon":"0","History":"22030","Speed_MPH":"128","ServeIndicator":"1"},{"ElapsedTime":"0:37:20","SetNo":"2","P1GamesWon":"2","P2GamesWon":"2","SetWinner":"0","GameNo":"5","GameWinner":"0","PointNumber":"63","PointWinner":"1","PointServer":"1","Speed_KMH":"197","P1Score":"40","P2Score":"15","PointTrack":"2","SetTrack":"-22","P1PointsWon":"0","P2PointsWon":"0","Ace":"0","Winner":"0","DoubleFault":"0","UnforcedError":"0","NetPoint":"0","BreakPoint":"0","BreakPointWon":"0","History":"21030","Speed_MPH":"122","ServeIndicator":"1"},{"ElapsedTime":"0:37:42","SetNo":"2","P1GamesWon":"3","P2GamesWon":"2","SetWinner":"0","GameNo":"5","GameWinner":"1","PointNumber":"64","PointWinner":"1","PointServer":"1","Speed_KMH":"148","P1Score":"0","P2Score":"0","PointTrack":"4","SetTrack":"-20","P1PointsWon":"0","P2PointsWon":"0","Ace":"0","Winner":"0","DoubleFault":"0","UnforcedError":"0","NetPoint":"0","BreakPoint":"0","BreakPointWon":"0","History":"21032","Speed_MPH":"92","ServeIndicator":"2"},{"ElapsedTime":"0:39:32","SetNo":"2","P1GamesWon":"3","P2GamesWon":"2","SetWinner":"0","GameNo":"6","GameWinner":"0","PointNumber":"65","PointWinner":"2","PointServer":"2","Speed_KMH":"170","P1Score":"0","P2Score":"15","PointTrack":"3","SetTrack":"-21","P1PointsWon":"0","P2PointsWon":"0","Ace":"0","Winner":"2","DoubleFault":"0","UnforcedError":"0","NetPoint":"0","BreakPoint":"0","BreakPointWon":"0","History":"21410","Speed_MPH":"105","ServeIndicator":"2"},{"ElapsedTime":"0:39:57","SetNo":"2","P1GamesWon":"3","P2GamesWon":"2","SetWinner":"0","GameNo":"6","GameWinner":"0","PointNumber":"66","PointWinner":"1","PointServer":"2","Speed_KMH":"143","P1Score":"15","P2Score":"15","PointTrack":"4","SetTrack":"-20","P1PointsWon":"0","P2PointsWon":"0","Ace":"0","Winner":"0","DoubleFault":"0","UnforcedError":"0","NetPoint":"0","BreakPoint":"0","BreakPointWon":"0","History":"21430","Speed_MPH":"88","ServeIndicator":"2"},{"ElapsedTime":"0:40:31","SetNo":"2","P1GamesWon":"3","P2GamesWon":"2","SetWinner":"0","GameNo":"6","GameWinner":"0","PointNumber":"67","PointWinner":"1","PointServer":"2","Speed_KMH":"0","P1Score":"30","P2Score":"15","PointTrack":"5","SetTrack":"-19","P1PointsWon":"0","P2PointsWon":"0","Ace":"0","Winner":"0","DoubleFault":"2","UnforcedError":"2","NetPoint":"0","BreakPoint":"0","BreakPointWon":"0","History":"25000","Speed_MPH":"0","ServeIndicator":"2"},{"ElapsedTime":"0:41:12","SetNo":"2","P1GamesWon":"3","P2GamesWon":"2","SetWinner":"0","GameNo":"6","GameWinner":"0","PointNumber":"68","PointWinner":"1","PointServer":"2","Speed_KMH":"143","P1Score":"40","P2Score":"15","PointTrack":"6","SetTrack":"-18","P1PointsWon":"0","P2PointsWon":"0","Ace":"0","Winner":"0","DoubleFault":"0","UnforcedError":"2","NetPoint":"0","BreakPoint":"0","BreakPointWon":"0","History":"21520","Speed_MPH":"88","ServeIndicator":"2"},{"ElapsedTime":"0:41:57","SetNo":"2","P1GamesWon":"3","P2GamesWon":"2","SetWinner":"0","GameNo":"6","GameWinner":"0","PointNumber":"69","PointWinner":"2","PointServer":"2","Speed_KMH":"169","P1Score":"40","P2Score":"30","PointTrack":"5","SetTrack":"-19","P1PointsWon":"0","P2PointsWon":"0","Ace":"0","Winner":"2","DoubleFault":"0","UnforcedError":"0","NetPoint":"0","BreakPoint":"1","BreakPointWon":"0","History":"21510","Speed_MPH":"105","ServeIndicator":"2"},{"ElapsedTime":"0:42:47","SetNo":"2","P1GamesWon":"3","P2GamesWon":"2","SetWinner":"0","GameNo":"6","GameWinner":"0","PointNumber":"70","PointWinner":"2","PointServer":"2","Speed_KMH":"152","P1Score":"40","P2Score":"40","PointTrack":"4","SetTrack":"-20","P1PointsWon":"0","P2PointsWon":"0","Ace":"0","Winner":"2","DoubleFault":"0","UnforcedError":"0","NetPoint":"0","BreakPoint":"1","BreakPointWon":"0","History":"22410","Speed_MPH":"94","ServeIndicator":"2"},{"ElapsedTime":"0:44:08","SetNo":"2","P1GamesWon":"3","P2GamesWon":"2","SetWinner":"0","GameNo":"6","GameWinner":"0","PointNumber":"71","PointWinner":"2","PointServer":"2","Speed_KMH":"168","P1Score":"40","P2Score":"AD","PointTrack":"3","SetTrack":"-21","P1PointsWon":"0","P2PointsWon":"0","Ace":"0","Winner":"0","DoubleFault":"0","UnforcedError":"1","NetPoint":"0","BreakPoint":"0","BreakPointWon":"0","History":"11420","Speed_MPH":"104","ServeIndicator":"2"},{"ElapsedTime":"0:44:23","SetNo":"2","P1GamesWon":"3","P2GamesWon":"2","SetWinner":"0","GameNo":"6","GameWinner":"0","PointNumber":"72","PointWinner":"1","PointServer":"2","Speed_KMH":"147","P1Score":"40","P2Score":"40","PointTrack":"4","SetTrack":"-20","P1PointsWon":"0","P2PointsWon":"0","Ace":"0","Winner":"1","DoubleFault":"0","UnforcedError":"0","NetPoint":"0","BreakPoint":"0","BreakPointWon":"0","History":"12010","Speed_MPH":"91","ServeIndicator":"2"},{"ElapsedTime":"0:45:02","SetNo":"2","P1GamesWon":"3","P2GamesWon":"2","SetWinner":"0","GameNo":"6","GameWinner":"0","PointNumber":"73","PointWinner":"2","PointServer":"2","Speed_KMH":"181","P1Score":"40","P2Score":"AD","PointTrack":"3","SetTrack":"-21","P1PointsWon":"0","P2PointsWon":"0","Ace":"0","Winner":"2","DoubleFault":"0","UnforcedError":"0","NetPoint":"0","BreakPoint":"0","BreakPointWon":"0","History":"21010","Speed_MPH":"112","ServeIndicator":"2"},{"ElapsedTime":"0:45:29","SetNo":"2","P1GamesWon":"3","P2GamesWon":"3","SetWinner":"0","GameNo":"6","GameWinner":"2","PointNumber":"74","PointWinner":"2","PointServer":"2","Speed_KMH":"204","P1Score":"0","P2Score":"0","PointTrack":"0","SetTrack":"-24","P1PointsWon":"0","P2PointsWon":"0","Ace":"0","Winner":"2","DoubleFault":"0","UnforcedError":"0","NetPoint":"0","BreakPoint":"0","BreakPointWon":"0","History":"24000","Speed_MPH":"126","ServeIndicator":"1"},{"ElapsedTime":"0:46:05","SetNo":"2","P1GamesWon":"3","P2GamesWon":"3","SetWinner":"0","GameNo":"7","GameWinner":"0","PointNumber":"75","PointWinner":"2","PointServer":"1","Speed_KMH":"170","P1Score":"0","P2Score":"15","PointTrack":"-1","SetTrack":"-25","P1PointsWon":"0","P2PointsWon":"0","Ace":"0","Winner":"0","DoubleFault":"0","UnforcedError":"0","NetPoint":"0","BreakPoint":"0","BreakPointWon":"0","History":"12430","Speed_MPH":"105","ServeIndicator":"1"},{"ElapsedTime":"0:46:26","SetNo":"2","P1GamesWon":"3","P2GamesWon":"3","SetWinner":"0","GameNo":"7","GameWinner":"0","PointNumber":"76","PointWinner":"2","PointServer":"1","Speed_KMH":"154","P1Score":"0","P2Score":"30","PointTrack":"-2","SetTrack":"-26","P1PointsWon":"0","P2PointsWon":"0","Ace":"0","Winner":"0","DoubleFault":"0","UnforcedError":"0","NetPoint":"0","BreakPoint":"0","BreakPointWon":"0","History":"12430","Speed_MPH":"95","ServeIndicator":"1"},{"ElapsedTime":"0:47:11","SetNo":"2","P1GamesWon":"3","P2GamesWon":"3","SetWinner":"0","GameNo":"7","GameWinner":"0","PointNumber":"77","PointWinner":"1","PointServer":"1","Speed_KMH":"177","P1Score":"15","P2Score":"30","PointTrack":"-1","SetTrack":"-25","P1PointsWon":"0","P2PointsWon":"0","Ace":"0","Winner":"1","DoubleFault":"0","UnforcedError":"0","NetPoint":"0","BreakPoint":"0","BreakPointWon":"0","History":"12410","Speed_MPH":"110","ServeIndicator":"1"},{"ElapsedTime":"0:48:05","SetNo":"2","P1GamesWon":"3","P2GamesWon":"3","SetWinner":"0","GameNo":"7","GameWinner":"0","PointNumber":"78","PointWinner":"1","PointServer":"1","Speed_KMH":"156","P1Score":"30","P2Score":"30","PointTrack":"0","SetTrack":"-24","P1PointsWon":"0","P2PointsWon":"0","Ace":"0","Winner":"1","DoubleFault":"0","UnforcedError":"0","NetPoint":"0","BreakPoint":"0","BreakPointWon":"0","History":"12010","Speed_MPH":"97","ServeIndicator":"1"},{"ElapsedTime":"0:48:20","SetNo":"2","P1GamesWon":"3","P2GamesWon":"3","SetWinner":"0","GameNo":"7","GameWinner":"0","PointNumber":"79","PointWinner":"1","PointServer":"1","Speed_KMH":"184","P1Score":"40","P2Score":"30","PointTrack":"1","SetTrack":"-23","P1PointsWon":"0","P2PointsWon":"0","Ace":"0","Winner":"0","DoubleFault":"0","UnforcedError":"0","NetPoint":"0","BreakPoint":"0","BreakPointWon":"0","History":"22030","Speed_MPH":"114","ServeIndicator":"1"},{"ElapsedTime":"0:48:38","SetNo":"2","P1GamesWon":"4","P2GamesWon":"3","SetWinner":"0","GameNo":"7","GameWinner":"1","PointNumber":"80","PointWinner":"1","PointServer":"1","Speed_KMH":"186","P1Score":"0","P2Score":"0","PointTrack":"4","SetTrack":"-20","P1PointsWon":"0","P2PointsWon":"0","Ace":"1","Winner":"1","DoubleFault":"0","UnforcedError":"0","NetPoint":"0","BreakPoint":"0","BreakPointWon":"0","History":"13000","Speed_MPH":"115","ServeIndicator":"2"},{"ElapsedTime":"0:50:03","SetNo":"2","P1GamesWon":"4","P2GamesWon":"3","SetWinner":"0","GameNo":"8","GameWinner":"0","PointNumber":"81","PointWinner":"2","PointServer":"2","Speed_KMH":"145","P1Score":"0","P2Score":"15","PointTrack":"3","SetTrack":"-21","P1PointsWon":"0","P2PointsWon":"0","Ace":"0","Winner":"0","DoubleFault":"0","UnforcedError":"1","NetPoint":"0","BreakPoint":"0","BreakPointWon":"0","History":"11020","Speed_MPH":"90","ServeIndicator":"2"},{"ElapsedTime":"0:50:39","SetNo":"2","P1GamesWon":"4","P2GamesWon":"3","SetWinner":"0","GameNo":"8","GameWinner":"0","PointNumber":"82","PointWinner":"2","PointServer":"2","Speed_KMH":"178","P1Score":"0","P2Score":"30","PointTrack":"2","SetTrack":"-22","P1PointsWon":"0","P2PointsWon":"0","Ace":"0","Winner":"0","DoubleFault":"0","UnforcedError":"0","NetPoint":"0","BreakPoint":"0","BreakPointWon":"0","History":"11030","Speed_MPH":"110","ServeIndicator":"2"},{"ElapsedTime":"0:50:59","SetNo":"2","P1GamesWon":"4","P2GamesWon":"3","SetWinner":"0","GameNo":"8","GameWinner":"0","PointNumber":"83","PointWinner":"2","PointServer":"2","Speed_KMH":"182","P1Score":"0","P2Score":"40","PointTrack":"1","SetTrack":"-23","P1PointsWon":"0","P2PointsWon":"0","Ace":"0","Winner":"2","DoubleFault":"0","UnforcedError":"0","NetPoint":"0","BreakPoint":"0","BreakPointWon":"0","History":"24000","Speed_MPH":"113","ServeIndicator":"2"},{"ElapsedTime":"0:51:18","SetNo":"2","P1GamesWon":"4","P2GamesWon":"3","SetWinner":"0","GameNo":"8","GameWinner":"0","PointNumber":"84","PointWinner":"1","PointServer":"2","Speed_KMH":"153","P1Score":"15","P2Score":"40","PointTrack":"2","SetTrack":"-22","P1PointsWon":"0","P2PointsWon":"0","Ace":"0","Winner":"0","DoubleFault":"0","UnforcedError":"0","NetPoint":"0","BreakPoint":"0","BreakPointWon":"0","History":"21430","Speed_MPH":"95","ServeIndicator":"2"},{"ElapsedTime":"0:52:31","SetNo":"2","P1GamesWon":"4","P2GamesWon":"4","SetWinner":"0","GameNo":"8","GameWinner":"2","PointNumber":"85","PointWinner":"2","PointServer":"2","Speed_KMH":"179","P1Score":"0","P2Score":"0","PointTrack":"0","SetTrack":"-24","P1PointsWon":"0","P2PointsWon":"0","Ace":"0","Winner":"2","DoubleFault":"0","UnforcedError":"0","NetPoint":"0","BreakPoint":"0","BreakPointWon":"0","History":"21512","Speed_MPH":"111","ServeIndicator":"1"},{"ElapsedTime":"0:53:22","SetNo":"2","P1GamesWon":"4","P2GamesWon":"4","SetWinner":"0","GameNo":"9","GameWinner":"0","PointNumber":"86","PointWinner":"1","PointServer":"1","Speed_KMH":"158","P1Score":"15","P2Score":"0","PointTrack":"1","SetTrack":"-23","P1PointsWon":"0","P2PointsWon":"0","Ace":"0","Winner":"0","DoubleFault":"0","UnforcedError":"0","NetPoint":"0","BreakPoint":"0","BreakPointWon":"0","History":"21430","Speed_MPH":"98","ServeIndicator":"1"},{"ElapsedTime":"0:53:52","SetNo":"2","P1GamesWon":"4","P2GamesWon":"4","SetWinner":"0","GameNo":"9","GameWinner":"0","PointNumber":"87","PointWinner":"1","PointServer":"1","Speed_KMH":"173","P1Score":"30","P2Score":"0","PointTrack":"2","SetTrack":"-22","P1PointsWon":"0","P2PointsWon":"0","Ace":"1","Winner":"1","DoubleFault":"0","UnforcedError":"0","NetPoint":"0","BreakPoint":"0","BreakPointWon":"0","History":"13000","Speed_MPH":"107","ServeIndicator":"1"},{"ElapsedTime":"0:54:09","SetNo":"2","P1GamesWon":"4","P2GamesWon":"4","SetWinner":"0","GameNo":"9","GameWinner":"0","PointNumber":"88","PointWinner":"2","PointServer":"1","Speed_KMH":"162","P1Score":"30","P2Score":"15","PointTrack":"1","SetTrack":"-23","P1PointsWon":"0","P2PointsWon":"0","Ace":"0","Winner":"0","DoubleFault":"0","UnforcedError":"0","NetPoint":"0","BreakPoint":"0","BreakPointWon":"0","History":"12430","Speed_MPH":"100","ServeIndicator":"1"},{"ElapsedTime":"0:54:45","SetNo":"2","P1GamesWon":"4","P2GamesWon":"4","SetWinner":"0","GameNo":"9","GameWinner":"0","PointNumber":"89","PointWinner":"2","PointServer":"1","Speed_KMH":"194","P1Score":"30","P2Score":"30","PointTrack":"0","SetTrack":"-24","P1PointsWon":"0","P2PointsWon":"0","Ace":"0","Winner":"0","DoubleFault":"0","UnforcedError":"0","NetPoint":"0","BreakPoint":"0","BreakPointWon":"0","History":"11430","Speed_MPH":"120","ServeIndicator":"1"},{"ElapsedTime":"0:55:08","SetNo":"2","P1GamesWon":"4","P2GamesWon":"4","SetWinner":"0","GameNo":"9","GameWinner":"0","PointNumber":"90","PointWinner":"1","PointServer":"1","Speed_KMH":"168","P1Score":"40","P2Score":"30","PointTrack":"1","SetTrack":"-23","P1PointsWon":"0","P2PointsWon":"0","Ace":"0","Winner":"0","DoubleFault":"0","UnforcedError":"0","NetPoint":"0","BreakPoint":"0","BreakPointWon":"0","History":"21030","Speed_MPH":"104","ServeIndicator":"1"},{"ElapsedTime":"0:55:42","SetNo":"2","P1GamesWon":"5","P2GamesWon":"4","SetWinner":"0","GameNo":"9","GameWinner":"1","PointNumber":"91","PointWinner":"1","PointServer":"1","Speed_KMH":"134","P1Score":"0","P2Score":"0","PointTrack":"4","SetTrack":"-20","P1PointsWon":"0","P2PointsWon":"0","Ace":"0","Winner":"0","DoubleFault":"0","UnforcedError":"0","NetPoint":"0","BreakPoint":"0","BreakPointWon":"0","History":"22032","Speed_MPH":"83","ServeIndicator":"2"},{"ElapsedTime":"0:57:15","SetNo":"2","P1GamesWon":"5","P2GamesWon":"4","SetWinner":"0","GameNo":"10","GameWinner":"0","PointNumber":"92","PointWinner":"2","PointServer":"2","Speed_KMH":"167","P1Score":"0","P2Score":"15","PointTrack":"3","SetTrack":"-21","P1PointsWon":"0","P2PointsWon":"0","Ace":"2","Winner":"2","DoubleFault":"0","UnforcedError":"0","NetPoint":"0","BreakPoint":"0","BreakPointWon":"0","History":"23000","Speed_MPH":"103","ServeIndicator":"2"},{"ElapsedTime":"0:57:30","SetNo":"2","P1GamesWon":"5","P2GamesWon":"4","SetWinner":"0","GameNo":"10","GameWinner":"0","PointNumber":"93","PointWinner":"2","PointServer":"2","Speed_KMH":"179","P1Score":"0","P2Score":"30","PointTrack":"2","SetTrack":"-22","P1PointsWon":"0","P2PointsWon":"0","Ace":"0","Winner":"2","DoubleFault":"0","UnforcedError":"0","NetPoint":"0","BreakPoint":"0","BreakPointWon":"0","History":"21410","Speed_MPH":"111","ServeIndicator":"2"},{"ElapsedTime":"0:57:48","SetNo":"2","P1GamesWon":"5","P2GamesWon":"4","SetWinner":"0","GameNo":"10","GameWinner":"0","PointNumber":"94","PointWinner":"1","PointServer":"2","Speed_KMH":"163","P1Score":"15","P2Score":"30","PointTrack":"3","SetTrack":"-21","P1PointsWon":"0","P2PointsWon":"0","Ace":"0","Winner":"1","DoubleFault":"0","UnforcedError":"0","NetPoint":"0","BreakPoint":"0","BreakPointWon":"0","History":"11010","Speed_MPH":"101","ServeIndicator":"2"},{"ElapsedTime":"0:58:22","SetNo":"2","P1GamesWon":"5","P2GamesWon":"4","SetWinner":"0","GameNo":"10","GameWinner":"0","PointNumber":"95","PointWinner":"1","PointServer":"2","Speed_KMH":"159","P1Score":"30","P2Score":"30","PointTrack":"4","SetTrack":"-20","P1PointsWon":"0","P2PointsWon":"0","Ace":"0","Winner":"0","DoubleFault":"0","UnforcedError":"0","NetPoint":"0","BreakPoint":"0","BreakPointWon":"0","History":"22430","Speed_MPH":"98","ServeIndicator":"2"},{"ElapsedTime":"0:59:13","SetNo":"2","P1GamesWon":"5","P2GamesWon":"4","SetWinner":"0","GameNo":"10","GameWinner":"0","PointNumber":"96","PointWinner":"2","PointServer":"2","Speed_KMH":"163","P1Score":"30","P2Score":"40","PointTrack":"3","SetTrack":"-21","P1PointsWon":"0","P2PointsWon":"0","Ace":"0","Winner":"2","DoubleFault":"0","UnforcedError":"0","NetPoint":"0","BreakPoint":"0","BreakPointWon":"0","History":"21410","Speed_MPH":"101","ServeIndicator":"2"},{"ElapsedTime":"0:59:47","SetNo":"2","P1GamesWon":"5","P2GamesWon":"5","SetWinner":"0","GameNo":"10","GameWinner":"2","PointNumber":"97","PointWinner":"2","PointServer":"2","Speed_KMH":"189","P1Score":"0","P2Score":"0","PointTrack":"0","SetTrack":"-24","P1PointsWon":"0","P2PointsWon":"0","Ace":"0","Winner":"0","DoubleFault":"0","UnforcedError":"0","NetPoint":"0","BreakPoint":"0","BreakPointWon":"0","History":"12432","Speed_MPH":"117","ServeIndicator":"1"},{"ElapsedTime":"1:00:22","SetNo":"2","P1GamesWon":"5","P2GamesWon":"5","SetWinner":"0","GameNo":"11","GameWinner":"0","PointNumber":"98","PointWinner":"1","PointServer":"1","Speed_KMH":"186","P1Score":"15","P2Score":"0","PointTrack":"1","SetTrack":"-23","P1PointsWon":"0","P2PointsWon":"0","Ace":"0","Winner":"0","DoubleFault":"0","UnforcedError":"2","NetPoint":"0","BreakPoint":"0","BreakPointWon":"0","History":"21020","Speed_MPH":"115","ServeIndicator":"1"},{"ElapsedTime":"1:00:45","SetNo":"2","P1GamesWon":"5","P2GamesWon":"5","SetWinner":"0","GameNo":"11","GameWinner":"0","PointNumber":"99","PointWinner":"2","PointServer":"1","Speed_KMH":"144","P1Score":"15","P2Score":"15","PointTrack":"0","SetTrack":"-24","P1PointsWon":"0","P2PointsWon":"0","Ace":"0","Winner":"0","DoubleFault":"0","UnforcedError":"0","NetPoint":"0","BreakPoint":"0","BreakPointWon":"0","History":"12430","Speed_MPH":"89","ServeIndicator":"1"},{"ElapsedTime":"1:01:15","SetNo":"2","P1GamesWon":"5","P2GamesWon":"5","SetWinner":"0","GameNo":"11","GameWinner":"0","PointNumber":"100","PointWinner":"1","PointServer":"1","Speed_KMH":"177","P1Score":"30","P2Score":"15","PointTrack":"1","SetTrack":"-23","P1PointsWon":"0","P2PointsWon":"0","Ace":"0","Winner":"0","DoubleFault":"0","UnforcedError":"0","NetPoint":"0","BreakPoint":"0","BreakPointWon":"0","History":"22430","Speed_MPH":"110","ServeIndicator":"1"},{"ElapsedTime":"1:01:44","SetNo":"2","P1GamesWon":"5","P2GamesWon":"5","SetWinner":"0","GameNo":"11","GameWinner":"0","PointNumber":"101","PointWinner":"1","PointServer":"1","Speed_KMH":"150","P1Score":"40","P2Score":"15","PointTrack":"2","SetTrack":"-22","P1PointsWon":"0","P2PointsWon":"0","Ace":"0","Winner":"0","DoubleFault":"0","UnforcedError":"0","NetPoint":"0","BreakPoint":"0","BreakPointWon":"0","History":"22030","Speed_MPH":"93","ServeIndicator":"1"},{"ElapsedTime":"1:02:13","SetNo":"2","P1GamesWon":"5","P2GamesWon":"5","SetWinner":"0","GameNo":"11","GameWinner":"0","PointNumber":"102","PointWinner":"2","PointServer":"1","Speed_KMH":"189","P1Score":"40","P2Score":"30","PointTrack":"1","SetTrack":"-23","P1PointsWon":"0","P2PointsWon":"0","Ace":"0","Winner":"2","DoubleFault":"0","UnforcedError":"0","NetPoint":"0","BreakPoint":"0","BreakPointWon":"0","History":"21510","Speed_MPH":"117","ServeIndicator":"1"},{"ElapsedTime":"1:02:40","SetNo":"2","P1GamesWon":"6","P2GamesWon":"5","SetWinner":"0","GameNo":"11","GameWinner":"1","PointNumber":"103","PointWinner":"1","PointServer":"1","Speed_KMH":"147","P1Score":"0","P2Score":"0","PointTrack":"4","SetTrack":"-20","P1PointsWon":"0","P2PointsWon":"0","Ace":"0","Winner":"0","DoubleFault":"0","UnforcedError":"2","NetPoint":"0","BreakPoint":"0","BreakPointWon":"0","History":"22022","Speed_MPH":"91","ServeIndicator":"2"},{"ElapsedTime":"1:04:08","SetNo":"2","P1GamesWon":"6","P2GamesWon":"5","SetWinner":"0","GameNo":"12","GameWinner":"0","PointNumber":"104","PointWinner":"2","PointServer":"2","Speed_KMH":"151","P1Score":"0","P2Score":"15","PointTrack":"3","SetTrack":"-21","P1PointsWon":"0","P2PointsWon":"0","Ace":"0","Winner":"2","DoubleFault":"0","UnforcedError":"0","NetPoint":"0","BreakPoint":"0","BreakPointWon":"0","History":"21410","Speed_MPH":"93","ServeIndicator":"2"},{"ElapsedTime":"1:04:42","SetNo":"2","P1GamesWon":"6","P2GamesWon":"5","SetWinner":"0","GameNo":"12","GameWinner":"0","PointNumber":"105","PointWinner":"2","PointServer":"2","Speed_KMH":"177","P1Score":"0","P2Score":"30","PointTrack":"2","SetTrack":"-22","P1PointsWon":"0","P2PointsWon":"0","Ace":"0","Winner":"0","DoubleFault":"0","UnforcedError":"0","NetPoint":"0","BreakPoint":"0","BreakPointWon":"0","History":"11030","Speed_MPH":"110","ServeIndicator":"2"},{"ElapsedTime":"1:05:03","SetNo":"2","P1GamesWon":"6","P2GamesWon":"5","SetWinner":"0","GameNo":"12","GameWinner":"0","PointNumber":"106","PointWinner":"2","PointServer":"2","Speed_KMH":"175","P1Score":"0","P2Score":"40","PointTrack":"1","SetTrack":"-23","P1PointsWon":"0","P2PointsWon":"0","Ace":"0","Winner":"0","DoubleFault":"0","UnforcedError":"0","NetPoint":"0","BreakPoint":"0","BreakPointWon":"0","History":"12030","Speed_MPH":"108","ServeIndicator":"2"},{"ElapsedTime":"1:05:26","SetNo":"2","P1GamesWon":"6","P2GamesWon":"6","SetWinner":"0","GameNo":"12","GameWinner":"2","PointNumber":"107","PointWinner":"2","PointServer":"2","Speed_KMH":"155","P1Score":"0","P2Score":"0","PointTrack":"0","SetTrack":"-24","P1PointsWon":"0","P2PointsWon":"0","Ace":"2","Winner":"2","DoubleFault":"0","UnforcedError":"0","NetPoint":"0","BreakPoint":"0","BreakPointWon":"0","History":"23000","Speed_MPH":"96","ServeIndicator":"1"},{"ElapsedTime":"1:06:10","SetNo":"2","P1GamesWon":"6","P2GamesWon":"6","SetWinner":"0","GameNo":"13","GameWinner":"0","PointNumber":"108","PointWinner":"1","PointServer":"1","Speed_KMH":"192","P1Score":"1","P2Score":"0","PointTrack":"1","SetTrack":"-23","P1PointsWon":"0","P2PointsWon":"0","Ace":"0","Winner":"0","DoubleFault":"0","UnforcedError":"0","NetPoint":"0","BreakPoint":"0","BreakPointWon":"0","History":"21030","Speed_MPH":"119","ServeIndicator":"2"},{"ElapsedTime":"1:06:33","SetNo":"2","P1GamesWon":"6","P2GamesWon":"6","SetWinner":"0","GameNo":"13","GameWinner":"0","PointNumber":"109","PointWinner":"2","PointServer":"2","Speed_KMH":"195","P1Score":"1","P2Score":"1","PointTrack":"0","SetTrack":"-24","P1PointsWon":"0","P2PointsWon":"0","Ace":"0","Winner":"2","DoubleFault":"0","UnforcedError":"0","NetPoint":"0","BreakPoint":"0","BreakPointWon":"0","History":"21010","Speed_MPH":"121","ServeIndicator":"2"},{"ElapsedTime":"1:06:56","SetNo":"2","P1GamesWon":"6","P2GamesWon":"6","SetWinner":"0","GameNo":"13","GameWinner":"0","PointNumber":"110","PointWinner":"2","PointServer":"2","Speed_KMH":"199","P1Score":"1","P2Score":"2","PointTrack":"-1","SetTrack":"-25","P1PointsWon":"0","P2PointsWon":"0","Ace":"0","Winner":"0","DoubleFault":"0","UnforcedError":"0","NetPoint":"0","BreakPoint":"0","BreakPointWon":"0","History":"11030","Speed_MPH":"123","ServeIndicator":"1"},{"ElapsedTime":"1:07:20","SetNo":"2","P1GamesWon":"6","P2GamesWon":"6","SetWinner":"0","GameNo":"13","GameWinner":"0","PointNumber":"111","PointWinner":"2","PointServer":"1","Speed_KMH":"152","P1Score":"1","P2Score":"3","PointTrack":"-2","SetTrack":"-26","P1PointsWon":"0","P2PointsWon":"0","Ace":"0","Winner":"2","DoubleFault":"0","UnforcedError":"0","NetPoint":"0","BreakPoint":"0","BreakPointWon":"0","History":"22010","Speed_MPH":"94","ServeIndicator":"1"},{"ElapsedTime":"1:07:53","SetNo":"2","P1GamesWon":"6","P2GamesWon":"6","SetWinner":"0","GameNo":"13","GameWinner":"0","PointNumber":"112","PointWinner":"2","PointServer":"1","Speed_KMH":"180","P1Score":"1","P2Score":"4","PointTrack":"-3","SetTrack":"-27","P1PointsWon":"0","P2PointsWon":"0","Ace":"0","Winner":"2","DoubleFault":"0","UnforcedError":"0","NetPoint":"0","BreakPoint":"0","BreakPointWon":"0","History":"21410","Speed_MPH":"111","ServeIndicator":"2"},{"ElapsedTime":"1:08:27","SetNo":"2","P1GamesWon":"6","P2GamesWon":"6","SetWinner":"0","GameNo":"13","GameWinner":"0","PointNumber":"113","PointWinner":"2","PointServer":"2","Speed_KMH":"150","P1Score":"1","P2Score":"5","PointTrack":"-4","SetTrack":"-28","P1PointsWon":"0","P2PointsWon":"0","Ace":"0","Winner":"0","DoubleFault":"0","UnforcedError":"1","NetPoint":"0","BreakPoint":"0","BreakPointWon":"0","History":"11020","Speed_MPH":"93","ServeIndicator":"2"},{"ElapsedTime":"1:09:50","SetNo":"2","P1GamesWon":"6","P2GamesWon":"6","SetWinner":"0","GameNo":"13","GameWinner":"0","PointNumber":"114","PointWinner":"2","PointServer":"2","Speed_KMH":"185","P1Score":"1","P2Score":"6","PointTrack":"-5","SetTrack":"-29","P1PointsWon":"0","P2PointsWon":"0","Ace":"2","Winner":"2","DoubleFault":"0","UnforcedError":"0","NetPoint":"0","BreakPoint":"0","BreakPointWon":"0","History":"23000","Speed_MPH":"115","ServeIndicator":"1"},{"ElapsedTime":"1:10:21","SetNo":"2","P1GamesWon":"6","P2GamesWon":"7","SetWinner":"2","GameNo":"13","GameWinner":"2","PointNumber":"115","PointWinner":"2","PointServer":"1","Speed_KMH":"151","P1Score":"0","P2Score":"0","PointTrack":"-8","SetTrack":"-48","P1PointsWon":"0","P2PointsWon":"0","Ace":"0","Winner":"0","DoubleFault":"0","UnforcedError":"0","NetPoint":"0","BreakPoint":"0","BreakPointWon":"0","History":"11434","Speed_MPH":"93","ServeIndicator":"2"}]